{
  "loio": "1dfec5536a51204be10000000a174cb4",
  "title": "Plain Vanilla Interest Rate Swap",
  "file_path": "1dfec5536a51204be10000000a174cb4.html",
  "page_id": 2555105061,
  "github_link": "",
  "toc_path": [
    "Treasury and Risk Management",
    "Risk Management",
    "Market Risk Analyzer",
    "Asset/Liability Management",
    "Examples",
    "Plain Vanilla Interest Rate Swap"
  ],
  "depth": 5,
  "body_html": "<!DOCTYPE html\n  SYSTEM \"about:legacy-compat\">\n<html lang=\"en-us\" dir=\"ltr\"><head><title>Plain Vanilla Interest Rate Swap</title><meta charset=\"utf-8\"><link rel=\"stylesheet\" type=\"text/css\" media=\"screen,projection\" href=\"/resource/css/style-v2.css\"><script type=\"text/javascript\" src=\"js/sap-strings.js\"></script></head><body class=\"en-us sap-light centered navigation-default enumeration-disabled\"><div id=\"d4h5-main-container\" class=\"container_12\" role=\"application\"><div id=\"d4h5-section-container\" class=\"grid_12\"><div id=\"d4h5-main-content\" class=\"grid_8 alpha omega\"><section><div class=\"page topic  - topic-topic \" id=\"loio1dfec5536a51204be10000000a174cb4\"><h1 class=\"title topictitle1\">Plain Vanilla Interest Rate Swap </h1><div class=\"body\">\n<p class=\"p\"> Payer swap\n</p>\n<p class=\"p\"> Nominal amount: EUR 100,000\n</p>\n<p class=\"p\"> Fixed interest: 6% nominal, annual interest payment, interest calculation method 360/360\n</p>\n<p class=\"p\"> Variable interest rate: 3-month euribor, interest calculation method act/365\n</p>\n<p class=\"p\"> Term: 12/05/2000 - 12/05/2003\n</p>\n<p class=\"p\"> Cash flow:\n</p>\n<div class=\"table-wrapper tablenoborder\"><table summary=\"\" class=\"table\" frame=\"border\" border=\"1\" rules=\"all\"><colgroup><col width=\"33.333333333333336%\"><col width=\"33.333333333333336%\"><col width=\"33.333333333333336%\"></colgroup><thead class=\"thead\" style=\"text-align:left;\"><tr class=\"row\"><th class=\"entry\" style=\"vertical-align:top;\" id=\"d216457e86\"><p class=\"p\"> Payment date\n</p></th><th class=\"entry\" style=\"vertical-align:top;\" id=\"d216457e90\"><p class=\"p\"> Payment amount\n</p></th><th class=\"entry\" style=\"vertical-align:top;\" id=\"d216457e94\"><p class=\"p\"> Type of flow\n</p></th></tr></thead><tbody class=\"tbody\"><tr class=\"row\"><td class=\"entry\" style=\"vertical-align:top;\" headers=\"d216457e86 \"><p class=\"p\"> 12/05/2000\n</p></td><td class=\"entry\" style=\"vertical-align:top;\" headers=\"d216457e90 \"><p class=\"p\"> EUR +100,000.00\n</p></td><td class=\"entry\" style=\"vertical-align:top;\" headers=\"d216457e94 \"><p class=\"p\"> Nominal amount increase (not relevant for posting)\n</p></td></tr><tr class=\"row\"><td class=\"entry\" style=\"vertical-align:top;\" headers=\"d216457e86 \"><p class=\"p\"> 12/05/2000\n</p></td><td class=\"entry\" style=\"vertical-align:top;\" headers=\"d216457e90 \"><p class=\"p\"> EUR -100,000.00\n</p></td><td class=\"entry\" style=\"vertical-align:top;\" headers=\"d216457e94 \"><p class=\"p\"> Nominal amount increase (not relevant for posting)\n</p></td></tr><tr class=\"row\"><td class=\"entry\" style=\"vertical-align:top;\" headers=\"d216457e86 \"><p class=\"p\"> 12/03/2001\n</p></td><td class=\"entry\" style=\"vertical-align:top;\" headers=\"d216457e90 \"><p class=\"p\"> EUR +0.00\n</p></td><td class=\"entry\" style=\"vertical-align:top;\" headers=\"d216457e94 \"><p class=\"p\"> Variable interest\n</p></td></tr><tr class=\"row\"><td class=\"entry\" style=\"vertical-align:top;\" headers=\"d216457e86 \"><p class=\"p\"> 12/06/2001\n</p></td><td class=\"entry\" style=\"vertical-align:top;\" headers=\"d216457e90 \"><p class=\"p\"> EUR +0.00\n</p></td><td class=\"entry\" style=\"vertical-align:top;\" headers=\"d216457e94 \"><p class=\"p\"> Variable interest\n</p></td></tr><tr class=\"row\"><td class=\"entry\" style=\"vertical-align:top;\" headers=\"d216457e86 \"><p class=\"p\"> 12/09/2001\n</p></td><td class=\"entry\" style=\"vertical-align:top;\" headers=\"d216457e90 \"><p class=\"p\"> EUR +0.00\n</p></td><td class=\"entry\" style=\"vertical-align:top;\" headers=\"d216457e94 \"><p class=\"p\"> Variable interest\n</p></td></tr><tr class=\"row\"><td class=\"entry\" style=\"vertical-align:top;\" headers=\"d216457e86 \"><p class=\"p\"> 12/05/2001\n</p></td><td class=\"entry\" style=\"vertical-align:top;\" headers=\"d216457e90 \"><p class=\"p\"> EUR +0.00\n</p></td><td class=\"entry\" style=\"vertical-align:top;\" headers=\"d216457e94 \"><p class=\"p\"> Variable interest\n</p></td></tr><tr class=\"row\"><td class=\"entry\" style=\"vertical-align:top;\" headers=\"d216457e86 \"><p class=\"p\"> 12/05/2001\n</p></td><td class=\"entry\" style=\"vertical-align:top;\" headers=\"d216457e90 \"><p class=\"p\"> EUR -6,000.00\n</p></td><td class=\"entry\" style=\"vertical-align:top;\" headers=\"d216457e94 \"><p class=\"p\"> Fixed interest\n</p></td></tr><tr class=\"row\"><td class=\"entry\" style=\"vertical-align:top;\" headers=\"d216457e86 \"><p class=\"p\"> 12/03/2002\n</p></td><td class=\"entry\" style=\"vertical-align:top;\" headers=\"d216457e90 \"><p class=\"p\"> EUR +0.00\n</p></td><td class=\"entry\" style=\"vertical-align:top;\" headers=\"d216457e94 \"><p class=\"p\"> Variable interest\n</p></td></tr><tr class=\"row\"><td class=\"entry\" style=\"vertical-align:top;\" headers=\"d216457e86 \"><p class=\"p\"> 12/06/2002\n</p></td><td class=\"entry\" style=\"vertical-align:top;\" headers=\"d216457e90 \"><p class=\"p\"> EUR +0.00\n</p></td><td class=\"entry\" style=\"vertical-align:top;\" headers=\"d216457e94 \"><p class=\"p\"> Variable interest\n</p></td></tr><tr class=\"row\"><td class=\"entry\" style=\"vertical-align:top;\" headers=\"d216457e86 \"><p class=\"p\"> 12/09/2002\n</p></td><td class=\"entry\" style=\"vertical-align:top;\" headers=\"d216457e90 \"><p class=\"p\"> EUR +0.00\n</p></td><td class=\"entry\" style=\"vertical-align:top;\" headers=\"d216457e94 \"><p class=\"p\"> Variable interest\n</p></td></tr><tr class=\"row\"><td class=\"entry\" style=\"vertical-align:top;\" headers=\"d216457e86 \"><p class=\"p\"> 12/05/2002\n</p></td><td class=\"entry\" style=\"vertical-align:top;\" headers=\"d216457e90 \"><p class=\"p\"> EUR +0.00\n</p></td><td class=\"entry\" style=\"vertical-align:top;\" headers=\"d216457e94 \"><p class=\"p\"> Variable interest\n</p></td></tr><tr class=\"row\"><td class=\"entry\" style=\"vertical-align:top;\" headers=\"d216457e86 \"><p class=\"p\"> 12/05/2002\n</p></td><td class=\"entry\" style=\"vertical-align:top;\" headers=\"d216457e90 \"><p class=\"p\"> EUR -6,000.00\n</p></td><td class=\"entry\" style=\"vertical-align:top;\" headers=\"d216457e94 \"><p class=\"p\"> Fixed interest\n</p></td></tr><tr class=\"row\"><td class=\"entry\" style=\"vertical-align:top;\" headers=\"d216457e86 \"><p class=\"p\"> 12/03/2003\n</p></td><td class=\"entry\" style=\"vertical-align:top;\" headers=\"d216457e90 \"><p class=\"p\"> EUR +0.00\n</p></td><td class=\"entry\" style=\"vertical-align:top;\" headers=\"d216457e94 \"><p class=\"p\"> Variable interest\n</p></td></tr><tr class=\"row\"><td class=\"entry\" style=\"vertical-align:top;\" headers=\"d216457e86 \"><p class=\"p\"> 12/06/2003\n</p></td><td class=\"entry\" style=\"vertical-align:top;\" headers=\"d216457e90 \"><p class=\"p\"> EUR +0.00\n</p></td><td class=\"entry\" style=\"vertical-align:top;\" headers=\"d216457e94 \"><p class=\"p\"> Variable interest\n</p></td></tr><tr class=\"row\"><td class=\"entry\" style=\"vertical-align:top;\" headers=\"d216457e86 \"><p class=\"p\"> 12/09/2003\n</p></td><td class=\"entry\" style=\"vertical-align:top;\" headers=\"d216457e90 \"><p class=\"p\"> EUR +0.00\n</p></td><td class=\"entry\" style=\"vertical-align:top;\" headers=\"d216457e94 \"><p class=\"p\"> Variable interest\n</p></td></tr><tr class=\"row\"><td class=\"entry\" style=\"vertical-align:top;\" headers=\"d216457e86 \"><p class=\"p\"> 12/05/2003\n</p></td><td class=\"entry\" style=\"vertical-align:top;\" headers=\"d216457e90 \"><p class=\"p\"> EUR +0.00\n</p></td><td class=\"entry\" style=\"vertical-align:top;\" headers=\"d216457e94 \"><p class=\"p\"> Variable interest\n</p></td></tr><tr class=\"row\"><td class=\"entry\" style=\"vertical-align:top;\" headers=\"d216457e86 \"><p class=\"p\"> 12/05/2003\n</p></td><td class=\"entry\" style=\"vertical-align:top;\" headers=\"d216457e90 \"><p class=\"p\"> EUR +100,000.00\n</p></td><td class=\"entry\" style=\"vertical-align:top;\" headers=\"d216457e94 \"><p class=\"p\"> Closing (not relevant for posting)\n</p></td></tr><tr class=\"row\"><td class=\"entry\" style=\"vertical-align:top;\" headers=\"d216457e86 \"><p class=\"p\"> 12/05/2003\n</p></td><td class=\"entry\" style=\"vertical-align:top;\" headers=\"d216457e90 \"><p class=\"p\"> EUR -100,000.00\n</p></td><td class=\"entry\" style=\"vertical-align:top;\" headers=\"d216457e94 \"><p class=\"p\"> Closing (not relevant for posting)\n</p></td></tr><tr class=\"row\"><td class=\"entry\" style=\"vertical-align:top;\" headers=\"d216457e86 \"><p class=\"p\"> 12/05/2003\n</p></td><td class=\"entry\" style=\"vertical-align:top;\" headers=\"d216457e90 \"><p class=\"p\"> EUR -6,000.00\n</p></td><td class=\"entry\" style=\"vertical-align:top;\" headers=\"d216457e94 \"><p class=\"p\"> Fixed interest\n</p></td></tr></tbody></table></div>\n<p class=\"p\"><img class=\"inline\" src=\"loio4822705364e7771ee10000000a174cb4_LowRes.png\" alt=\"\" title=\"\"> The nominal amounts displayed are fictitious capital amounts. The interest rates on the variable side were not fixed yet.\n</p>\n<p class=\"p\"><img class=\"inline\" src=\"loio7213c753b1081d4be10000000a174cb4_LowRes.png\" alt=\"\" title=\"\"><span class=\"ph emphasis emphasis\">Evaluation date</span> : 10/29/2000\n</p>\n<p class=\"p\"><span class=\"ph emphasis emphasis\">Settings in the ALM valuation type</span>\n</p>\n<ul class=\"ul\"><li class=\"li\"><p class=\"p\"> Outflow indicator: <span class=\"ph uicontrol\">Negative outflows on same balance sheet side</span>\n</p></li><li class=\"li\"><p class=\"p\"> Interest calculation method: <span class=\"ph uicontrol\">act/365</span>\n</p></li><li class=\"li\"><p class=\"p\"> Balance sheet volume in net interest income: <span class=\"ph uicontrol\">Off-balance sheet transactions not included</span>\n</p></li></ul>\n<div class=\"section\"><section class=\"section\" type=\"Average position (interest commitment)\"><h2 class=\"section_title\">Average position (interest commitment)</h2>\n<div class=\"table-wrapper tablenoborder\"><table summary=\"\" class=\"table\" frame=\"border\" border=\"1\" rules=\"all\"><colgroup><col width=\"11.11111111111111%\"><col width=\"11.11111111111111%\"><col width=\"11.11111111111111%\"><col width=\"11.11111111111111%\"><col width=\"11.11111111111111%\"><col width=\"11.11111111111111%\"><col width=\"11.11111111111111%\"><col width=\"11.11111111111111%\"><col width=\"11.11111111111111%\"></colgroup><thead class=\"thead\" style=\"text-align:left;\"><tr class=\"row\"><th class=\"entry\" style=\"vertical-align:top;\" id=\"d216457e407\"><p class=\"p\"> Maturity band date\n</p></th><th class=\"entry\" style=\"vertical-align:top;\" id=\"d216457e411\"><p class=\"p\"> Asset volume\n</p></th><th class=\"entry\" style=\"vertical-align:top;\" id=\"d216457e415\"><p class=\"p\"> Asset-side interest\n</p></th><th class=\"entry\" style=\"vertical-align:top;\" id=\"d216457e419\"><p class=\"p\"> Asset-side opportunity interest\n</p></th><th class=\"entry\" style=\"vertical-align:top;\" id=\"d216457e423\"><p class=\"p\"> Liability volume\n</p></th><th class=\"entry\" style=\"vertical-align:top;\" id=\"d216457e427\"><p class=\"p\"> Liability-side interest\n</p></th><th class=\"entry\" style=\"vertical-align:top;\" id=\"d216457e431\"><p class=\"p\"> Liability-side opportunity interest\n</p></th><th class=\"entry\" style=\"vertical-align:top;\" id=\"d216457e435\"><p class=\"p\"> Asset gap\n</p></th><th class=\"entry\" style=\"vertical-align:top;\" id=\"d216457e439\"><p class=\"p\"> Liability gap\n</p></th></tr></thead><tbody class=\"tbody\"><tr class=\"row\"><td class=\"entry\" style=\"vertical-align:top;\" headers=\"d216457e407 \"><p class=\"p\"> 10/29/2000\n</p></td><td class=\"entry\" style=\"vertical-align:top;\" headers=\"d216457e411 \"><p class=\"p\">\n</p></td><td class=\"entry\" style=\"vertical-align:top;\" headers=\"d216457e415 \"><p class=\"p\">\n</p></td><td class=\"entry\" style=\"vertical-align:top;\" headers=\"d216457e419 \"><p class=\"p\">\n</p></td><td class=\"entry\" style=\"vertical-align:top;\" headers=\"d216457e423 \"><p class=\"p\">\n</p></td><td class=\"entry\" style=\"vertical-align:top;\" headers=\"d216457e427 \"><p class=\"p\">\n</p></td><td class=\"entry\" style=\"vertical-align:top;\" headers=\"d216457e431 \"><p class=\"p\">\n</p></td><td class=\"entry\" style=\"vertical-align:top;\" headers=\"d216457e435 \"><p class=\"p\">\n</p></td><td class=\"entry\" style=\"vertical-align:top;\" headers=\"d216457e439 \"><p class=\"p\">\n</p></td></tr><tr class=\"row\"><td class=\"entry\" style=\"vertical-align:top;\" headers=\"d216457e407 \"><p class=\"p\"> 10/30/2001\n</p></td><td class=\"entry\" style=\"vertical-align:top;\" headers=\"d216457e411 \"><p class=\"p\">\n</p></td><td class=\"entry\" style=\"vertical-align:top;\" headers=\"d216457e415 \"><p class=\"p\">\n</p></td><td class=\"entry\" style=\"vertical-align:top;\" headers=\"d216457e419 \"><p class=\"p\">\n</p></td><td class=\"entry\" style=\"vertical-align:top;\" headers=\"d216457e423 \"><p class=\"p\"> 90,163.93\n</p></td><td class=\"entry\" style=\"vertical-align:top;\" headers=\"d216457e427 \"><p class=\"p\"> 6.00\n</p></td><td class=\"entry\" style=\"vertical-align:top;\" headers=\"d216457e431 \"><p class=\"p\"> 6.00\n</p></td><td class=\"entry\" style=\"vertical-align:top;\" headers=\"d216457e435 \"><p class=\"p\">\n</p></td><td class=\"entry\" style=\"vertical-align:top;\" headers=\"d216457e439 \"><p class=\"p\"> 90,163.93\n</p></td></tr><tr class=\"row\"><td class=\"entry\" style=\"vertical-align:top;\" headers=\"d216457e407 \"><p class=\"p\"> 01/30/2002\n</p></td><td class=\"entry\" style=\"vertical-align:top;\" headers=\"d216457e411 \"><p class=\"p\">\n</p></td><td class=\"entry\" style=\"vertical-align:top;\" headers=\"d216457e415 \"><p class=\"p\">\n</p></td><td class=\"entry\" style=\"vertical-align:top;\" headers=\"d216457e419 \"><p class=\"p\">\n</p></td><td class=\"entry\" style=\"vertical-align:top;\" headers=\"d216457e423 \"><p class=\"p\"> 100,000.00\n</p></td><td class=\"entry\" style=\"vertical-align:top;\" headers=\"d216457e427 \"><p class=\"p\"> 6.00\n</p></td><td class=\"entry\" style=\"vertical-align:top;\" headers=\"d216457e431 \"><p class=\"p\"> 6.00\n</p></td><td class=\"entry\" style=\"vertical-align:top;\" headers=\"d216457e435 \"><p class=\"p\">\n</p></td><td class=\"entry\" style=\"vertical-align:top;\" headers=\"d216457e439 \"><p class=\"p\"> 100,000.00\n</p></td></tr><tr class=\"row\"><td class=\"entry\" style=\"vertical-align:top;\" headers=\"d216457e407 \"><p class=\"p\"> 01/30/2003\n</p></td><td class=\"entry\" style=\"vertical-align:top;\" headers=\"d216457e411 \"><p class=\"p\">\n</p></td><td class=\"entry\" style=\"vertical-align:top;\" headers=\"d216457e415 \"><p class=\"p\">\n</p></td><td class=\"entry\" style=\"vertical-align:top;\" headers=\"d216457e419 \"><p class=\"p\">\n</p></td><td class=\"entry\" style=\"vertical-align:top;\" headers=\"d216457e423 \"><p class=\"p\"> 100,000.00\n</p></td><td class=\"entry\" style=\"vertical-align:top;\" headers=\"d216457e427 \"><p class=\"p\"> 6.00\n</p></td><td class=\"entry\" style=\"vertical-align:top;\" headers=\"d216457e431 \"><p class=\"p\"> 6.00\n</p></td><td class=\"entry\" style=\"vertical-align:top;\" headers=\"d216457e435 \"><p class=\"p\">\n</p></td><td class=\"entry\" style=\"vertical-align:top;\" headers=\"d216457e439 \"><p class=\"p\"> 100,000.00\n</p></td></tr><tr class=\"row\"><td class=\"entry\" style=\"vertical-align:top;\" headers=\"d216457e407 \"><p class=\"p\"> 04/30/2004\n</p></td><td class=\"entry\" style=\"vertical-align:top;\" headers=\"d216457e411 \"><p class=\"p\">\n</p></td><td class=\"entry\" style=\"vertical-align:top;\" headers=\"d216457e415 \"><p class=\"p\">\n</p></td><td class=\"entry\" style=\"vertical-align:top;\" headers=\"d216457e419 \"><p class=\"p\">\n</p></td><td class=\"entry\" style=\"vertical-align:top;\" headers=\"d216457e423 \"><p class=\"p\"> 67,543.86\n</p></td><td class=\"entry\" style=\"vertical-align:top;\" headers=\"d216457e427 \"><p class=\"p\"> 6.00\n</p></td><td class=\"entry\" style=\"vertical-align:top;\" headers=\"d216457e431 \"><p class=\"p\"> 6.00\n</p></td><td class=\"entry\" style=\"vertical-align:top;\" headers=\"d216457e435 \"><p class=\"p\">\n</p></td><td class=\"entry\" style=\"vertical-align:top;\" headers=\"d216457e439 \"><p class=\"p\"> 67,543.86\n</p></td></tr></tbody></table></div>\n<p class=\"p\"><img class=\"inline\" src=\"loio4822705364e7771ee10000000a174cb4_LowRes.png\" alt=\"\" title=\"\"> Since this is the average position evaluation for the interest commitment, and the 3-month euribor has not been fixed for 05/12/2000 or any of the subsequent dates, the asset-side columns remain empty. The same applies to the key date position and maturity evaluations for the interest commitment .\n</p>\n<p class=\"p\"><img class=\"inline\" src=\"loio4822705364e7771ee10000000a174cb4_LowRes.png\" alt=\"\" title=\"\"> How is the average liability volume of EUR 90,163.93 calculated?\n</p>\n<p class=\"p\"> In the period from 10/30/2000 to 12/04/2000 (36 days) the liability volume is EUR 0.00, whereas in the period from 12/05/2000 to 10/30/2001 (330 days) it is EUR 100,000.00. Based on this data, the average liability volume is calculated as follows:\n</p>\n<ul class=\"ul\"><li class=\"li\"><p class=\"p\"> (36 x 0.00+330 x 100,000.00)/366 = EUR 90,163.93\n</p></li></ul>\n<p class=\"p\"><img class=\"inline\" src=\"loio4822705364e7771ee10000000a174cb4_LowRes.png\" alt=\"\" title=\"\"> In the case of derivative transactions, the product interest is used as the <a class=\"xref\" href=\"ccfdc5536a51204be10000000a174cb4.html\">opportunity interest</a> . You can also transfer an opportunity interest rate as an external key figure. If you want to use this option, you have to set the <span class=\"ph uicontrol\">OI determination</span> indicator in the ALM valuation type to <span class=\"ph uicontrol\">External key figure</span> .\n</p>\n</section></div>\n<div class=\"section\"><section class=\"section\" type=\"Average position (capital commitment)\"><h2 class=\"section_title\">Average position (capital commitment)</h2>\n<div class=\"table-wrapper tablenoborder\"><table summary=\"\" class=\"table\" frame=\"border\" border=\"1\" rules=\"all\"><colgroup><col width=\"11.11111111111111%\"><col width=\"11.11111111111111%\"><col width=\"11.11111111111111%\"><col width=\"11.11111111111111%\"><col width=\"11.11111111111111%\"><col width=\"11.11111111111111%\"><col width=\"11.11111111111111%\"><col width=\"11.11111111111111%\"><col width=\"11.11111111111111%\"></colgroup><thead class=\"thead\" style=\"text-align:left;\"><tr class=\"row\"><th class=\"entry\" style=\"vertical-align:top;\" id=\"d216457e684\"><p class=\"p\"> Maturity band date\n</p></th><th class=\"entry\" style=\"vertical-align:top;\" id=\"d216457e688\"><p class=\"p\"> Asset volume\n</p></th><th class=\"entry\" style=\"vertical-align:top;\" id=\"d216457e692\"><p class=\"p\"> Asset-side interest\n</p></th><th class=\"entry\" style=\"vertical-align:top;\" id=\"d216457e696\"><p class=\"p\"> Asset-side opportunity interest\n</p></th><th class=\"entry\" style=\"vertical-align:top;\" id=\"d216457e700\"><p class=\"p\"> Liability volume\n</p></th><th class=\"entry\" style=\"vertical-align:top;\" id=\"d216457e704\"><p class=\"p\"> Liability-side interest\n</p></th><th class=\"entry\" style=\"vertical-align:top;\" id=\"d216457e708\"><p class=\"p\"> Liability-side opportunity interest\n</p></th><th class=\"entry\" style=\"vertical-align:top;\" id=\"d216457e712\"><p class=\"p\"> Asset gap\n</p></th><th class=\"entry\" style=\"vertical-align:top;\" id=\"d216457e716\"><p class=\"p\"> Liability gap\n</p></th></tr></thead><tbody class=\"tbody\"><tr class=\"row\"><td class=\"entry\" style=\"vertical-align:top;\" headers=\"d216457e684 \"><p class=\"p\"> 10/29/2000\n</p></td><td class=\"entry\" style=\"vertical-align:top;\" headers=\"d216457e688 \"><p class=\"p\">\n</p></td><td class=\"entry\" style=\"vertical-align:top;\" headers=\"d216457e692 \"><p class=\"p\">\n</p></td><td class=\"entry\" style=\"vertical-align:top;\" headers=\"d216457e696 \"><p class=\"p\">\n</p></td><td class=\"entry\" style=\"vertical-align:top;\" headers=\"d216457e700 \"><p class=\"p\">\n</p></td><td class=\"entry\" style=\"vertical-align:top;\" headers=\"d216457e704 \"><p class=\"p\">\n</p></td><td class=\"entry\" style=\"vertical-align:top;\" headers=\"d216457e708 \"><p class=\"p\">\n</p></td><td class=\"entry\" style=\"vertical-align:top;\" headers=\"d216457e712 \"><p class=\"p\">\n</p></td><td class=\"entry\" style=\"vertical-align:top;\" headers=\"d216457e716 \"><p class=\"p\">\n</p></td></tr><tr class=\"row\"><td class=\"entry\" style=\"vertical-align:top;\" headers=\"d216457e684 \"><p class=\"p\"> 10/30/2001\n</p></td><td class=\"entry\" style=\"vertical-align:top;\" headers=\"d216457e688 \"><p class=\"p\"> 90,163.93\n</p></td><td class=\"entry\" style=\"vertical-align:top;\" headers=\"d216457e692 \"><p class=\"p\"> 3.537\n</p></td><td class=\"entry\" style=\"vertical-align:top;\" headers=\"d216457e696 \"><p class=\"p\"> 3.537\n</p></td><td class=\"entry\" style=\"vertical-align:top;\" headers=\"d216457e700 \"><p class=\"p\"> 90,163.93\n</p></td><td class=\"entry\" style=\"vertical-align:top;\" headers=\"d216457e704 \"><p class=\"p\"> 6.00\n</p></td><td class=\"entry\" style=\"vertical-align:top;\" headers=\"d216457e708 \"><p class=\"p\"> 6.00\n</p></td><td class=\"entry\" style=\"vertical-align:top;\" headers=\"d216457e712 \"><p class=\"p\">\n</p></td><td class=\"entry\" style=\"vertical-align:top;\" headers=\"d216457e716 \"><p class=\"p\">\n</p></td></tr><tr class=\"row\"><td class=\"entry\" style=\"vertical-align:top;\" headers=\"d216457e684 \"><p class=\"p\"> 01/30/2002\n</p></td><td class=\"entry\" style=\"vertical-align:top;\" headers=\"d216457e688 \"><p class=\"p\"> 100,000.00\n</p></td><td class=\"entry\" style=\"vertical-align:top;\" headers=\"d216457e692 \"><p class=\"p\"> 3.037\n</p></td><td class=\"entry\" style=\"vertical-align:top;\" headers=\"d216457e696 \"><p class=\"p\"> 3.037\n</p></td><td class=\"entry\" style=\"vertical-align:top;\" headers=\"d216457e700 \"><p class=\"p\"> 100,000.00\n</p></td><td class=\"entry\" style=\"vertical-align:top;\" headers=\"d216457e704 \"><p class=\"p\"> 6.00\n</p></td><td class=\"entry\" style=\"vertical-align:top;\" headers=\"d216457e708 \"><p class=\"p\"> 6.00\n</p></td><td class=\"entry\" style=\"vertical-align:top;\" headers=\"d216457e712 \"><p class=\"p\">\n</p></td><td class=\"entry\" style=\"vertical-align:top;\" headers=\"d216457e716 \"><p class=\"p\">\n</p></td></tr><tr class=\"row\"><td class=\"entry\" style=\"vertical-align:top;\" headers=\"d216457e684 \"><p class=\"p\"> 01/30/2003\n</p></td><td class=\"entry\" style=\"vertical-align:top;\" headers=\"d216457e688 \"><p class=\"p\"> 100,000.00\n</p></td><td class=\"entry\" style=\"vertical-align:top;\" headers=\"d216457e692 \"><p class=\"p\"> 2.658\n</p></td><td class=\"entry\" style=\"vertical-align:top;\" headers=\"d216457e696 \"><p class=\"p\"> 2.658\n</p></td><td class=\"entry\" style=\"vertical-align:top;\" headers=\"d216457e700 \"><p class=\"p\"> 100,000.00\n</p></td><td class=\"entry\" style=\"vertical-align:top;\" headers=\"d216457e704 \"><p class=\"p\"> 6.00\n</p></td><td class=\"entry\" style=\"vertical-align:top;\" headers=\"d216457e708 \"><p class=\"p\"> 6.00\n</p></td><td class=\"entry\" style=\"vertical-align:top;\" headers=\"d216457e712 \"><p class=\"p\">\n</p></td><td class=\"entry\" style=\"vertical-align:top;\" headers=\"d216457e716 \"><p class=\"p\">\n</p></td></tr><tr class=\"row\"><td class=\"entry\" style=\"vertical-align:top;\" headers=\"d216457e684 \"><p class=\"p\"> 04/30/2004\n</p></td><td class=\"entry\" style=\"vertical-align:top;\" headers=\"d216457e688 \"><p class=\"p\"> 67,543.86\n</p></td><td class=\"entry\" style=\"vertical-align:top;\" headers=\"d216457e692 \"><p class=\"p\"> 3.540\n</p></td><td class=\"entry\" style=\"vertical-align:top;\" headers=\"d216457e696 \"><p class=\"p\"> 3.540\n</p></td><td class=\"entry\" style=\"vertical-align:top;\" headers=\"d216457e700 \"><p class=\"p\"> 67,543.86\n</p></td><td class=\"entry\" style=\"vertical-align:top;\" headers=\"d216457e704 \"><p class=\"p\"> 6.00\n</p></td><td class=\"entry\" style=\"vertical-align:top;\" headers=\"d216457e708 \"><p class=\"p\"> 6.00\n</p></td><td class=\"entry\" style=\"vertical-align:top;\" headers=\"d216457e712 \"><p class=\"p\">\n</p></td><td class=\"entry\" style=\"vertical-align:top;\" headers=\"d216457e716 \"><p class=\"p\">\n</p></td></tr></tbody></table></div>\n<p class=\"p\"><img class=\"inline\" src=\"loio4822705364e7771ee10000000a174cb4_LowRes.png\" alt=\"\" title=\"\"> In the average position evaluation for the capital commitment, the variable side of the swap is shown as well. The forward rate determined by the system for the respective <a class=\"xref\" href=\"0402c55368511d4be10000000a174cb4.html\">maturity band date</a> is displayed as the asset-side interest rate. The same applies to the key date position and maturity evaluations for the capital commitment .\n</p>\n<p class=\"p\"> Settings in the ALM valuation type\n</p>\n<ul class=\"ul\"><li class=\"li\"><p class=\"p\"> Outflow indicator: <span class=\"ph uicontrol\">Negative outflows on same balance sheet side</span>\n</p></li><li class=\"li\"><p class=\"p\"> Interest calculation method: <span class=\"ph uicontrol\">act/365</span>\n</p></li><li class=\"li\"><p class=\"p\"> Balance sheet volume in net interest income: <span class=\"ph uicontrol\">Off-balance sheet transactions not included</span>\n</p></li></ul>\n</section></div>\n<div class=\"section\"><section class=\"section\" type=\"Key date position (interest commitment)\"><h2 class=\"section_title\">Key date position (interest commitment)</h2>\n<div class=\"table-wrapper tablenoborder\"><table summary=\"\" class=\"table\" frame=\"border\" border=\"1\" rules=\"all\"><colgroup><col width=\"11.11111111111111%\"><col width=\"11.11111111111111%\"><col width=\"11.11111111111111%\"><col width=\"11.11111111111111%\"><col width=\"11.11111111111111%\"><col width=\"11.11111111111111%\"><col width=\"11.11111111111111%\"><col width=\"11.11111111111111%\"><col width=\"11.11111111111111%\"></colgroup><thead class=\"thead\" style=\"text-align:left;\"><tr class=\"row\"><th class=\"entry\" style=\"vertical-align:top;\" id=\"d216457e961\"><p class=\"p\"> Maturity band date\n</p></th><th class=\"entry\" style=\"vertical-align:top;\" id=\"d216457e965\"><p class=\"p\"> Asset volume\n</p></th><th class=\"entry\" style=\"vertical-align:top;\" id=\"d216457e969\"><p class=\"p\"> Asset-side interest\n</p></th><th class=\"entry\" style=\"vertical-align:top;\" id=\"d216457e973\"><p class=\"p\"> Asset-side opportunity interest\n</p></th><th class=\"entry\" style=\"vertical-align:top;\" id=\"d216457e977\"><p class=\"p\"> Liability volume\n</p></th><th class=\"entry\" style=\"vertical-align:top;\" id=\"d216457e981\"><p class=\"p\"> Liability-side interest\n</p></th><th class=\"entry\" style=\"vertical-align:top;\" id=\"d216457e985\"><p class=\"p\"> Liability-side opportunity interest\n</p></th><th class=\"entry\" style=\"vertical-align:top;\" id=\"d216457e989\"><p class=\"p\"> Asset gap\n</p></th><th class=\"entry\" style=\"vertical-align:top;\" id=\"d216457e993\"><p class=\"p\"> Liability gap\n</p></th></tr></thead><tbody class=\"tbody\"><tr class=\"row\"><td class=\"entry\" style=\"vertical-align:top;\" headers=\"d216457e961 \"><p class=\"p\"> 10/29/2000\n</p></td><td class=\"entry\" style=\"vertical-align:top;\" headers=\"d216457e965 \"><p class=\"p\">\n</p></td><td class=\"entry\" style=\"vertical-align:top;\" headers=\"d216457e969 \"><p class=\"p\">\n</p></td><td class=\"entry\" style=\"vertical-align:top;\" headers=\"d216457e973 \"><p class=\"p\">\n</p></td><td class=\"entry\" style=\"vertical-align:top;\" headers=\"d216457e977 \"><p class=\"p\">\n</p></td><td class=\"entry\" style=\"vertical-align:top;\" headers=\"d216457e981 \"><p class=\"p\">\n</p></td><td class=\"entry\" style=\"vertical-align:top;\" headers=\"d216457e985 \"><p class=\"p\">\n</p></td><td class=\"entry\" style=\"vertical-align:top;\" headers=\"d216457e989 \"><p class=\"p\">\n</p></td><td class=\"entry\" style=\"vertical-align:top;\" headers=\"d216457e993 \"><p class=\"p\">\n</p></td></tr><tr class=\"row\"><td class=\"entry\" style=\"vertical-align:top;\" headers=\"d216457e961 \"><p class=\"p\"> 10/30/2001\n</p></td><td class=\"entry\" style=\"vertical-align:top;\" headers=\"d216457e965 \"><p class=\"p\">\n</p></td><td class=\"entry\" style=\"vertical-align:top;\" headers=\"d216457e969 \"><p class=\"p\">\n</p></td><td class=\"entry\" style=\"vertical-align:top;\" headers=\"d216457e973 \"><p class=\"p\">\n</p></td><td class=\"entry\" style=\"vertical-align:top;\" headers=\"d216457e977 \"><p class=\"p\"> 100,000.00\n</p></td><td class=\"entry\" style=\"vertical-align:top;\" headers=\"d216457e981 \"><p class=\"p\"> 6.00\n</p></td><td class=\"entry\" style=\"vertical-align:top;\" headers=\"d216457e985 \"><p class=\"p\"> 6.00\n</p></td><td class=\"entry\" style=\"vertical-align:top;\" headers=\"d216457e989 \"><p class=\"p\">\n</p></td><td class=\"entry\" style=\"vertical-align:top;\" headers=\"d216457e993 \"><p class=\"p\"> 100,000.00\n</p></td></tr><tr class=\"row\"><td class=\"entry\" style=\"vertical-align:top;\" headers=\"d216457e961 \"><p class=\"p\"> 01/30/2002\n</p></td><td class=\"entry\" style=\"vertical-align:top;\" headers=\"d216457e965 \"><p class=\"p\">\n</p></td><td class=\"entry\" style=\"vertical-align:top;\" headers=\"d216457e969 \"><p class=\"p\">\n</p></td><td class=\"entry\" style=\"vertical-align:top;\" headers=\"d216457e973 \"><p class=\"p\">\n</p></td><td class=\"entry\" style=\"vertical-align:top;\" headers=\"d216457e977 \"><p class=\"p\"> 100,000.00\n</p></td><td class=\"entry\" style=\"vertical-align:top;\" headers=\"d216457e981 \"><p class=\"p\"> 6.00\n</p></td><td class=\"entry\" style=\"vertical-align:top;\" headers=\"d216457e985 \"><p class=\"p\"> 6.00\n</p></td><td class=\"entry\" style=\"vertical-align:top;\" headers=\"d216457e989 \"><p class=\"p\">\n</p></td><td class=\"entry\" style=\"vertical-align:top;\" headers=\"d216457e993 \"><p class=\"p\"> 100,000.00\n</p></td></tr><tr class=\"row\"><td class=\"entry\" style=\"vertical-align:top;\" headers=\"d216457e961 \"><p class=\"p\"> 01/30/2003\n</p></td><td class=\"entry\" style=\"vertical-align:top;\" headers=\"d216457e965 \"><p class=\"p\">\n</p></td><td class=\"entry\" style=\"vertical-align:top;\" headers=\"d216457e969 \"><p class=\"p\">\n</p></td><td class=\"entry\" style=\"vertical-align:top;\" headers=\"d216457e973 \"><p class=\"p\">\n</p></td><td class=\"entry\" style=\"vertical-align:top;\" headers=\"d216457e977 \"><p class=\"p\"> 100,000.00\n</p></td><td class=\"entry\" style=\"vertical-align:top;\" headers=\"d216457e981 \"><p class=\"p\"> 6.00\n</p></td><td class=\"entry\" style=\"vertical-align:top;\" headers=\"d216457e985 \"><p class=\"p\"> 6.00\n</p></td><td class=\"entry\" style=\"vertical-align:top;\" headers=\"d216457e989 \"><p class=\"p\">\n</p></td><td class=\"entry\" style=\"vertical-align:top;\" headers=\"d216457e993 \"><p class=\"p\"> 100,000.00\n</p></td></tr><tr class=\"row\"><td class=\"entry\" style=\"vertical-align:top;\" headers=\"d216457e961 \"><p class=\"p\"> 04/30/2004\n</p></td><td class=\"entry\" style=\"vertical-align:top;\" headers=\"d216457e965 \"><p class=\"p\">\n</p></td><td class=\"entry\" style=\"vertical-align:top;\" headers=\"d216457e969 \"><p class=\"p\">\n</p></td><td class=\"entry\" style=\"vertical-align:top;\" headers=\"d216457e973 \"><p class=\"p\">\n</p></td><td class=\"entry\" style=\"vertical-align:top;\" headers=\"d216457e977 \"><p class=\"p\">\n</p></td><td class=\"entry\" style=\"vertical-align:top;\" headers=\"d216457e981 \"><p class=\"p\">\n</p></td><td class=\"entry\" style=\"vertical-align:top;\" headers=\"d216457e985 \"><p class=\"p\">\n</p></td><td class=\"entry\" style=\"vertical-align:top;\" headers=\"d216457e989 \"><p class=\"p\">\n</p></td><td class=\"entry\" style=\"vertical-align:top;\" headers=\"d216457e993 \"><p class=\"p\">\n</p></td></tr></tbody></table></div>\n</section></div>\n<div class=\"section\"><section class=\"section\" type=\"Key date position (capital commitment)\"><h2 class=\"section_title\">Key date position (capital commitment)</h2>\n<div class=\"table-wrapper tablenoborder\"><table summary=\"\" class=\"table\" frame=\"border\" border=\"1\" rules=\"all\"><colgroup><col width=\"11.11111111111111%\"><col width=\"11.11111111111111%\"><col width=\"11.11111111111111%\"><col width=\"11.11111111111111%\"><col width=\"11.11111111111111%\"><col width=\"11.11111111111111%\"><col width=\"11.11111111111111%\"><col width=\"11.11111111111111%\"><col width=\"11.11111111111111%\"></colgroup><thead class=\"thead\" style=\"text-align:left;\"><tr class=\"row\"><th class=\"entry\" style=\"vertical-align:top;\" id=\"d216457e1203\"><p class=\"p\"> Maturity band date\n</p></th><th class=\"entry\" style=\"vertical-align:top;\" id=\"d216457e1207\"><p class=\"p\"> Asset volume\n</p></th><th class=\"entry\" style=\"vertical-align:top;\" id=\"d216457e1211\"><p class=\"p\"> Asset-side interest\n</p></th><th class=\"entry\" style=\"vertical-align:top;\" id=\"d216457e1215\"><p class=\"p\"> Asset-side opportunity interest\n</p></th><th class=\"entry\" style=\"vertical-align:top;\" id=\"d216457e1219\"><p class=\"p\"> Liability volume\n</p></th><th class=\"entry\" style=\"vertical-align:top;\" id=\"d216457e1223\"><p class=\"p\"> Liability-side interest\n</p></th><th class=\"entry\" style=\"vertical-align:top;\" id=\"d216457e1227\"><p class=\"p\"> Liability-side opportunity interest\n</p></th><th class=\"entry\" style=\"vertical-align:top;\" id=\"d216457e1231\"><p class=\"p\"> Asset gap\n</p></th><th class=\"entry\" style=\"vertical-align:top;\" id=\"d216457e1235\"><p class=\"p\"> Liability gap\n</p></th></tr></thead><tbody class=\"tbody\"><tr class=\"row\"><td class=\"entry\" style=\"vertical-align:top;\" headers=\"d216457e1203 \"><p class=\"p\"> 10/29/2000\n</p></td><td class=\"entry\" style=\"vertical-align:top;\" headers=\"d216457e1207 \"><p class=\"p\">\n</p></td><td class=\"entry\" style=\"vertical-align:top;\" headers=\"d216457e1211 \"><p class=\"p\">\n</p></td><td class=\"entry\" style=\"vertical-align:top;\" headers=\"d216457e1215 \"><p class=\"p\">\n</p></td><td class=\"entry\" style=\"vertical-align:top;\" headers=\"d216457e1219 \"><p class=\"p\">\n</p></td><td class=\"entry\" style=\"vertical-align:top;\" headers=\"d216457e1223 \"><p class=\"p\">\n</p></td><td class=\"entry\" style=\"vertical-align:top;\" headers=\"d216457e1227 \"><p class=\"p\">\n</p></td><td class=\"entry\" style=\"vertical-align:top;\" headers=\"d216457e1231 \"><p class=\"p\">\n</p></td><td class=\"entry\" style=\"vertical-align:top;\" headers=\"d216457e1235 \"><p class=\"p\">\n</p></td></tr><tr class=\"row\"><td class=\"entry\" style=\"vertical-align:top;\" headers=\"d216457e1203 \"><p class=\"p\"> 10/30/2001\n</p></td><td class=\"entry\" style=\"vertical-align:top;\" headers=\"d216457e1207 \"><p class=\"p\"> 100,000.00\n</p></td><td class=\"entry\" style=\"vertical-align:top;\" headers=\"d216457e1211 \"><p class=\"p\"> 3.345\n</p></td><td class=\"entry\" style=\"vertical-align:top;\" headers=\"d216457e1215 \"><p class=\"p\"> 3.345\n</p></td><td class=\"entry\" style=\"vertical-align:top;\" headers=\"d216457e1219 \"><p class=\"p\"> 100,000.00\n</p></td><td class=\"entry\" style=\"vertical-align:top;\" headers=\"d216457e1223 \"><p class=\"p\"> 6.00\n</p></td><td class=\"entry\" style=\"vertical-align:top;\" headers=\"d216457e1227 \"><p class=\"p\"> 6.00\n</p></td><td class=\"entry\" style=\"vertical-align:top;\" headers=\"d216457e1231 \"><p class=\"p\">\n</p></td><td class=\"entry\" style=\"vertical-align:top;\" headers=\"d216457e1235 \"><p class=\"p\">\n</p></td></tr><tr class=\"row\"><td class=\"entry\" style=\"vertical-align:top;\" headers=\"d216457e1203 \"><p class=\"p\"> 01/30/2002\n</p></td><td class=\"entry\" style=\"vertical-align:top;\" headers=\"d216457e1207 \"><p class=\"p\"> 100,000.00\n</p></td><td class=\"entry\" style=\"vertical-align:top;\" headers=\"d216457e1211 \"><p class=\"p\"> 2.848\n</p></td><td class=\"entry\" style=\"vertical-align:top;\" headers=\"d216457e1215 \"><p class=\"p\"> 2.848\n</p></td><td class=\"entry\" style=\"vertical-align:top;\" headers=\"d216457e1219 \"><p class=\"p\"> 100,000.00\n</p></td><td class=\"entry\" style=\"vertical-align:top;\" headers=\"d216457e1223 \"><p class=\"p\"> 6.00\n</p></td><td class=\"entry\" style=\"vertical-align:top;\" headers=\"d216457e1227 \"><p class=\"p\"> 6.00\n</p></td><td class=\"entry\" style=\"vertical-align:top;\" headers=\"d216457e1231 \"><p class=\"p\">\n</p></td><td class=\"entry\" style=\"vertical-align:top;\" headers=\"d216457e1235 \"><p class=\"p\">\n</p></td></tr><tr class=\"row\"><td class=\"entry\" style=\"vertical-align:top;\" headers=\"d216457e1203 \"><p class=\"p\"> 01/30/2003\n</p></td><td class=\"entry\" style=\"vertical-align:top;\" headers=\"d216457e1207 \"><p class=\"p\"> 100,000.00\n</p></td><td class=\"entry\" style=\"vertical-align:top;\" headers=\"d216457e1211 \"><p class=\"p\"> 3.309\n</p></td><td class=\"entry\" style=\"vertical-align:top;\" headers=\"d216457e1215 \"><p class=\"p\"> 3.309\n</p></td><td class=\"entry\" style=\"vertical-align:top;\" headers=\"d216457e1219 \"><p class=\"p\"> 100,000.00\n</p></td><td class=\"entry\" style=\"vertical-align:top;\" headers=\"d216457e1223 \"><p class=\"p\"> 6.00\n</p></td><td class=\"entry\" style=\"vertical-align:top;\" headers=\"d216457e1227 \"><p class=\"p\"> 6.00\n</p></td><td class=\"entry\" style=\"vertical-align:top;\" headers=\"d216457e1231 \"><p class=\"p\">\n</p></td><td class=\"entry\" style=\"vertical-align:top;\" headers=\"d216457e1235 \"><p class=\"p\">\n</p></td></tr><tr class=\"row\"><td class=\"entry\" style=\"vertical-align:top;\" headers=\"d216457e1203 \"><p class=\"p\"> 04/30/2004\n</p></td><td class=\"entry\" style=\"vertical-align:top;\" headers=\"d216457e1207 \"><p class=\"p\">\n</p></td><td class=\"entry\" style=\"vertical-align:top;\" headers=\"d216457e1211 \"><p class=\"p\">\n</p></td><td class=\"entry\" style=\"vertical-align:top;\" headers=\"d216457e1215 \"><p class=\"p\">\n</p></td><td class=\"entry\" style=\"vertical-align:top;\" headers=\"d216457e1219 \"><p class=\"p\">\n</p></td><td class=\"entry\" style=\"vertical-align:top;\" headers=\"d216457e1223 \"><p class=\"p\">\n</p></td><td class=\"entry\" style=\"vertical-align:top;\" headers=\"d216457e1227 \"><p class=\"p\">\n</p></td><td class=\"entry\" style=\"vertical-align:top;\" headers=\"d216457e1231 \"><p class=\"p\">\n</p></td><td class=\"entry\" style=\"vertical-align:top;\" headers=\"d216457e1235 \"><p class=\"p\">\n</p></td></tr></tbody></table></div>\n<p class=\"p\"><span class=\"ph emphasis emphasis\">Settings in the ALM valuation type</span>\n</p>\n<ul class=\"ul\"><li class=\"li\"><p class=\"p\"> Outflow indicator: <span class=\"ph uicontrol\">Negative outflows on same balance sheet side</span>\n</p></li><li class=\"li\"><p class=\"p\"> Interest calculation method: <span class=\"ph uicontrol\">act/365</span>\n</p></li><li class=\"li\"><p class=\"p\"> Balance sheet volume in net interest income: <span class=\"ph uicontrol\">Off-balance sheet transactions not included</span>\n</p></li></ul>\n</section></div>\n<div class=\"section\"><section class=\"section\" type=\"Maturity evaluation (interest commitment)\"><h2 class=\"section_title\">Maturity evaluation (interest commitment)</h2>\n<div class=\"table-wrapper tablenoborder\"><table summary=\"\" class=\"table\" frame=\"border\" border=\"1\" rules=\"all\"><colgroup><col width=\"11.11111111111111%\"><col width=\"11.11111111111111%\"><col width=\"11.11111111111111%\"><col width=\"11.11111111111111%\"><col width=\"11.11111111111111%\"><col width=\"11.11111111111111%\"><col width=\"11.11111111111111%\"><col width=\"11.11111111111111%\"><col width=\"11.11111111111111%\"></colgroup><thead class=\"thead\" style=\"text-align:left;\"><tr class=\"row\"><th class=\"entry\" style=\"vertical-align:top;\" id=\"d216457e1473\"><p class=\"p\"> Maturity band date\n</p></th><th class=\"entry\" style=\"vertical-align:top;\" id=\"d216457e1477\"><p class=\"p\"> Asset-side outflow\n</p></th><th class=\"entry\" style=\"vertical-align:top;\" id=\"d216457e1481\"><p class=\"p\"> Asset-side interest\n</p></th><th class=\"entry\" style=\"vertical-align:top;\" id=\"d216457e1485\"><p class=\"p\"> Asset-side opportunity interest\n</p></th><th class=\"entry\" style=\"vertical-align:top;\" id=\"d216457e1489\"><p class=\"p\"> Liability-side outflow\n</p></th><th class=\"entry\" style=\"vertical-align:top;\" id=\"d216457e1493\"><p class=\"p\"> Liability-side interest\n</p></th><th class=\"entry\" style=\"vertical-align:top;\" id=\"d216457e1497\"><p class=\"p\"> Liability-side opportunity interest\n</p></th><th class=\"entry\" style=\"vertical-align:top;\" id=\"d216457e1501\"><p class=\"p\"> Asset gap\n</p></th><th class=\"entry\" style=\"vertical-align:top;\" id=\"d216457e1505\"><p class=\"p\"> Liability gap\n</p></th></tr></thead><tbody class=\"tbody\"><tr class=\"row\"><td class=\"entry\" style=\"vertical-align:top;\" headers=\"d216457e1473 \"><p class=\"p\"> 10/29/2000\n</p></td><td class=\"entry\" style=\"vertical-align:top;\" headers=\"d216457e1477 \"><p class=\"p\">\n</p></td><td class=\"entry\" style=\"vertical-align:top;\" headers=\"d216457e1481 \"><p class=\"p\">\n</p></td><td class=\"entry\" style=\"vertical-align:top;\" headers=\"d216457e1485 \"><p class=\"p\">\n</p></td><td class=\"entry\" style=\"vertical-align:top;\" headers=\"d216457e1489 \"><p class=\"p\">\n</p></td><td class=\"entry\" style=\"vertical-align:top;\" headers=\"d216457e1493 \"><p class=\"p\">\n</p></td><td class=\"entry\" style=\"vertical-align:top;\" headers=\"d216457e1497 \"><p class=\"p\">\n</p></td><td class=\"entry\" style=\"vertical-align:top;\" headers=\"d216457e1501 \"><p class=\"p\">\n</p></td><td class=\"entry\" style=\"vertical-align:top;\" headers=\"d216457e1505 \"><p class=\"p\">\n</p></td></tr><tr class=\"row\"><td class=\"entry\" style=\"vertical-align:top;\" headers=\"d216457e1473 \"><p class=\"p\"> 10/30/2001\n</p></td><td class=\"entry\" style=\"vertical-align:top;\" headers=\"d216457e1477 \"><p class=\"p\">\n</p></td><td class=\"entry\" style=\"vertical-align:top;\" headers=\"d216457e1481 \"><p class=\"p\">\n</p></td><td class=\"entry\" style=\"vertical-align:top;\" headers=\"d216457e1485 \"><p class=\"p\">\n</p></td><td class=\"entry\" style=\"vertical-align:top;\" headers=\"d216457e1489 \"><p class=\"p\"> -100,000.00\n</p></td><td class=\"entry\" style=\"vertical-align:top;\" headers=\"d216457e1493 \"><p class=\"p\"> 6.00\n</p></td><td class=\"entry\" style=\"vertical-align:top;\" headers=\"d216457e1497 \"><p class=\"p\"> 6.00\n</p></td><td class=\"entry\" style=\"vertical-align:top;\" headers=\"d216457e1501 \"><p class=\"p\"> 100,000.00\n</p></td><td class=\"entry\" style=\"vertical-align:top;\" headers=\"d216457e1505 \"><p class=\"p\">\n</p></td></tr><tr class=\"row\"><td class=\"entry\" style=\"vertical-align:top;\" headers=\"d216457e1473 \"><p class=\"p\"> 01/30/2002\n</p></td><td class=\"entry\" style=\"vertical-align:top;\" headers=\"d216457e1477 \"><p class=\"p\">\n</p></td><td class=\"entry\" style=\"vertical-align:top;\" headers=\"d216457e1481 \"><p class=\"p\">\n</p></td><td class=\"entry\" style=\"vertical-align:top;\" headers=\"d216457e1485 \"><p class=\"p\">\n</p></td><td class=\"entry\" style=\"vertical-align:top;\" headers=\"d216457e1489 \"><p class=\"p\">\n</p></td><td class=\"entry\" style=\"vertical-align:top;\" headers=\"d216457e1493 \"><p class=\"p\">\n</p></td><td class=\"entry\" style=\"vertical-align:top;\" headers=\"d216457e1497 \"><p class=\"p\">\n</p></td><td class=\"entry\" style=\"vertical-align:top;\" headers=\"d216457e1501 \"><p class=\"p\">\n</p></td><td class=\"entry\" style=\"vertical-align:top;\" headers=\"d216457e1505 \"><p class=\"p\">\n</p></td></tr><tr class=\"row\"><td class=\"entry\" style=\"vertical-align:top;\" headers=\"d216457e1473 \"><p class=\"p\"> 01/30/2003\n</p></td><td class=\"entry\" style=\"vertical-align:top;\" headers=\"d216457e1477 \"><p class=\"p\">\n</p></td><td class=\"entry\" style=\"vertical-align:top;\" headers=\"d216457e1481 \"><p class=\"p\">\n</p></td><td class=\"entry\" style=\"vertical-align:top;\" headers=\"d216457e1485 \"><p class=\"p\">\n</p></td><td class=\"entry\" style=\"vertical-align:top;\" headers=\"d216457e1489 \"><p class=\"p\">\n</p></td><td class=\"entry\" style=\"vertical-align:top;\" headers=\"d216457e1493 \"><p class=\"p\">\n</p></td><td class=\"entry\" style=\"vertical-align:top;\" headers=\"d216457e1497 \"><p class=\"p\">\n</p></td><td class=\"entry\" style=\"vertical-align:top;\" headers=\"d216457e1501 \"><p class=\"p\">\n</p></td><td class=\"entry\" style=\"vertical-align:top;\" headers=\"d216457e1505 \"><p class=\"p\">\n</p></td></tr><tr class=\"row\"><td class=\"entry\" style=\"vertical-align:top;\" headers=\"d216457e1473 \"><p class=\"p\"> 04/30/2004\n</p></td><td class=\"entry\" style=\"vertical-align:top;\" headers=\"d216457e1477 \"><p class=\"p\">\n</p></td><td class=\"entry\" style=\"vertical-align:top;\" headers=\"d216457e1481 \"><p class=\"p\">\n</p></td><td class=\"entry\" style=\"vertical-align:top;\" headers=\"d216457e1485 \"><p class=\"p\">\n</p></td><td class=\"entry\" style=\"vertical-align:top;\" headers=\"d216457e1489 \"><p class=\"p\"> 100,000.00\n</p></td><td class=\"entry\" style=\"vertical-align:top;\" headers=\"d216457e1493 \"><p class=\"p\"> 6.00\n</p></td><td class=\"entry\" style=\"vertical-align:top;\" headers=\"d216457e1497 \"><p class=\"p\"> 6.00\n</p></td><td class=\"entry\" style=\"vertical-align:top;\" headers=\"d216457e1501 \"><p class=\"p\">\n</p></td><td class=\"entry\" style=\"vertical-align:top;\" headers=\"d216457e1505 \"><p class=\"p\"> 100,000.00\n</p></td></tr></tbody></table></div>\n<p class=\"p\"><img class=\"inline\" src=\"loio4822705364e7771ee10000000a174cb4_LowRes.png\" alt=\"\" title=\"\"> The <span class=\"ph uicontrol\">negative outflows on same balance sheet side</span> setting in the ALM valuation type causes the system to display the liability-side inflow of EUR 100,000.00 in the liability-side outflow column with a minus sign (maturity band date 10/30/01). If you want the liability-side inflow to be displayed as an asset-side outflow, choose the default setting <span class=\"ph uicontrol\">negative outflows on other balance sheet side</span> .\n</p>\n</section></div>\n<div class=\"section\"><section class=\"section\" type=\"Maturity evaluation (capital commitment)\"><h2 class=\"section_title\">Maturity evaluation (capital commitment)</h2>\n<div class=\"table-wrapper tablenoborder\"><table summary=\"\" class=\"table\" frame=\"border\" border=\"1\" rules=\"all\"><colgroup><col width=\"11.11111111111111%\"><col width=\"11.11111111111111%\"><col width=\"11.11111111111111%\"><col width=\"11.11111111111111%\"><col width=\"11.11111111111111%\"><col width=\"11.11111111111111%\"><col width=\"11.11111111111111%\"><col width=\"11.11111111111111%\"><col width=\"11.11111111111111%\"></colgroup><thead class=\"thead\" style=\"text-align:left;\"><tr class=\"row\"><th class=\"entry\" style=\"vertical-align:top;\" id=\"d216457e1726\"><p class=\"p\"> Maturity band date\n</p></th><th class=\"entry\" style=\"vertical-align:top;\" id=\"d216457e1730\"><p class=\"p\"> Asset-side outflow\n</p></th><th class=\"entry\" style=\"vertical-align:top;\" id=\"d216457e1734\"><p class=\"p\"> Asset-side interest\n</p></th><th class=\"entry\" style=\"vertical-align:top;\" id=\"d216457e1738\"><p class=\"p\"> Asset-side opportunity interest\n</p></th><th class=\"entry\" style=\"vertical-align:top;\" id=\"d216457e1742\"><p class=\"p\"> Liability-side outflow\n</p></th><th class=\"entry\" style=\"vertical-align:top;\" id=\"d216457e1746\"><p class=\"p\"> Liability-side interest\n</p></th><th class=\"entry\" style=\"vertical-align:top;\" id=\"d216457e1750\"><p class=\"p\"> Liability-side opportunity interest\n</p></th><th class=\"entry\" style=\"vertical-align:top;\" id=\"d216457e1754\"><p class=\"p\"> Asset gap\n</p></th><th class=\"entry\" style=\"vertical-align:top;\" id=\"d216457e1758\"><p class=\"p\"> Liability gap\n</p></th></tr></thead><tbody class=\"tbody\"><tr class=\"row\"><td class=\"entry\" style=\"vertical-align:top;\" headers=\"d216457e1726 \"><p class=\"p\"> 10/29/2000\n</p></td><td class=\"entry\" style=\"vertical-align:top;\" headers=\"d216457e1730 \"><p class=\"p\">\n</p></td><td class=\"entry\" style=\"vertical-align:top;\" headers=\"d216457e1734 \"><p class=\"p\">\n</p></td><td class=\"entry\" style=\"vertical-align:top;\" headers=\"d216457e1738 \"><p class=\"p\">\n</p></td><td class=\"entry\" style=\"vertical-align:top;\" headers=\"d216457e1742 \"><p class=\"p\">\n</p></td><td class=\"entry\" style=\"vertical-align:top;\" headers=\"d216457e1746 \"><p class=\"p\">\n</p></td><td class=\"entry\" style=\"vertical-align:top;\" headers=\"d216457e1750 \"><p class=\"p\">\n</p></td><td class=\"entry\" style=\"vertical-align:top;\" headers=\"d216457e1754 \"><p class=\"p\">\n</p></td><td class=\"entry\" style=\"vertical-align:top;\" headers=\"d216457e1758 \"><p class=\"p\">\n</p></td></tr><tr class=\"row\"><td class=\"entry\" style=\"vertical-align:top;\" headers=\"d216457e1726 \"><p class=\"p\"> 10/30/2001\n</p></td><td class=\"entry\" style=\"vertical-align:top;\" headers=\"d216457e1730 \"><p class=\"p\"> -100,000.00\n</p></td><td class=\"entry\" style=\"vertical-align:top;\" headers=\"d216457e1734 \"><p class=\"p\"> 2.804\n</p></td><td class=\"entry\" style=\"vertical-align:top;\" headers=\"d216457e1738 \"><p class=\"p\"> 2.804\n</p></td><td class=\"entry\" style=\"vertical-align:top;\" headers=\"d216457e1742 \"><p class=\"p\"> -100,000.00\n</p></td><td class=\"entry\" style=\"vertical-align:top;\" headers=\"d216457e1746 \"><p class=\"p\"> 6.00\n</p></td><td class=\"entry\" style=\"vertical-align:top;\" headers=\"d216457e1750 \"><p class=\"p\"> 6.00\n</p></td><td class=\"entry\" style=\"vertical-align:top;\" headers=\"d216457e1754 \"><p class=\"p\">\n</p></td><td class=\"entry\" style=\"vertical-align:top;\" headers=\"d216457e1758 \"><p class=\"p\">\n</p></td></tr><tr class=\"row\"><td class=\"entry\" style=\"vertical-align:top;\" headers=\"d216457e1726 \"><p class=\"p\"> 01/30/2002\n</p></td><td class=\"entry\" style=\"vertical-align:top;\" headers=\"d216457e1730 \"><p class=\"p\">\n</p></td><td class=\"entry\" style=\"vertical-align:top;\" headers=\"d216457e1734 \"><p class=\"p\">\n</p></td><td class=\"entry\" style=\"vertical-align:top;\" headers=\"d216457e1738 \"><p class=\"p\">\n</p></td><td class=\"entry\" style=\"vertical-align:top;\" headers=\"d216457e1742 \"><p class=\"p\">\n</p></td><td class=\"entry\" style=\"vertical-align:top;\" headers=\"d216457e1746 \"><p class=\"p\">\n</p></td><td class=\"entry\" style=\"vertical-align:top;\" headers=\"d216457e1750 \"><p class=\"p\">\n</p></td><td class=\"entry\" style=\"vertical-align:top;\" headers=\"d216457e1754 \"><p class=\"p\">\n</p></td><td class=\"entry\" style=\"vertical-align:top;\" headers=\"d216457e1758 \"><p class=\"p\">\n</p></td></tr><tr class=\"row\"><td class=\"entry\" style=\"vertical-align:top;\" headers=\"d216457e1726 \"><p class=\"p\"> 01/30/2003\n</p></td><td class=\"entry\" style=\"vertical-align:top;\" headers=\"d216457e1730 \"><p class=\"p\">\n</p></td><td class=\"entry\" style=\"vertical-align:top;\" headers=\"d216457e1734 \"><p class=\"p\">\n</p></td><td class=\"entry\" style=\"vertical-align:top;\" headers=\"d216457e1738 \"><p class=\"p\">\n</p></td><td class=\"entry\" style=\"vertical-align:top;\" headers=\"d216457e1742 \"><p class=\"p\">\n</p></td><td class=\"entry\" style=\"vertical-align:top;\" headers=\"d216457e1746 \"><p class=\"p\">\n</p></td><td class=\"entry\" style=\"vertical-align:top;\" headers=\"d216457e1750 \"><p class=\"p\">\n</p></td><td class=\"entry\" style=\"vertical-align:top;\" headers=\"d216457e1754 \"><p class=\"p\">\n</p></td><td class=\"entry\" style=\"vertical-align:top;\" headers=\"d216457e1758 \"><p class=\"p\">\n</p></td></tr><tr class=\"row\"><td class=\"entry\" style=\"vertical-align:top;\" headers=\"d216457e1726 \"><p class=\"p\"> 04/30/2004\n</p></td><td class=\"entry\" style=\"vertical-align:top;\" headers=\"d216457e1730 \"><p class=\"p\"> 100,000.00\n</p></td><td class=\"entry\" style=\"vertical-align:top;\" headers=\"d216457e1734 \"><p class=\"p\"> 4.017\n</p></td><td class=\"entry\" style=\"vertical-align:top;\" headers=\"d216457e1738 \"><p class=\"p\"> 4.017\n</p></td><td class=\"entry\" style=\"vertical-align:top;\" headers=\"d216457e1742 \"><p class=\"p\"> 100,000.00\n</p></td><td class=\"entry\" style=\"vertical-align:top;\" headers=\"d216457e1746 \"><p class=\"p\"> 6.00\n</p></td><td class=\"entry\" style=\"vertical-align:top;\" headers=\"d216457e1750 \"><p class=\"p\"> 6.00\n</p></td><td class=\"entry\" style=\"vertical-align:top;\" headers=\"d216457e1754 \"><p class=\"p\">\n</p></td><td class=\"entry\" style=\"vertical-align:top;\" headers=\"d216457e1758 \"><p class=\"p\">\n</p></td></tr></tbody></table></div>\n<p class=\"p\"><span class=\"ph emphasis emphasis\">Settings in the ALM valuation type</span>\n</p>\n<ul class=\"ul\"><li class=\"li\"><p class=\"p\"> Outflow indicator: <span class=\"ph uicontrol\">Negative outflows on same balance sheet side</span>\n</p></li><li class=\"li\"><p class=\"p\"> Interest calculation method: <span class=\"ph uicontrol\">act/365</span>\n</p></li><li class=\"li\"><p class=\"p\"> Balance sheet volume in net interest income: <span class=\"ph uicontrol\">Off-balance sheet transactions not included</span>\n</p></li></ul>\n</section></div>\n<div class=\"section\"><section class=\"section\" type=\"Cash flow evaluation\"><h2 class=\"section_title\">Cash flow evaluation</h2>\n<div class=\"table-wrapper tablenoborder\"><table summary=\"\" class=\"table\" frame=\"border\" border=\"1\" rules=\"all\"><colgroup><col width=\"25%\"><col width=\"25%\"><col width=\"25%\"><col width=\"25%\"></colgroup><thead class=\"thead\" style=\"text-align:left;\"><tr class=\"row\"><th class=\"entry\" style=\"vertical-align:top;\" id=\"d216457e1992\"><p class=\"p\"> Maturity band date\n</p></th><th class=\"entry\" style=\"vertical-align:top;\" id=\"d216457e1996\"><p class=\"p\"> Inpayment\n</p></th><th class=\"entry\" style=\"vertical-align:top;\" id=\"d216457e2000\"><p class=\"p\"> Disbursement\n</p></th><th class=\"entry\" style=\"vertical-align:top;\" id=\"d216457e2004\"><p class=\"p\"> Gap\n</p></th></tr></thead><tbody class=\"tbody\"><tr class=\"row\"><td class=\"entry\" style=\"vertical-align:top;\" headers=\"d216457e1992 \"><p class=\"p\"> 10/29/2000\n</p></td><td class=\"entry\" style=\"vertical-align:top;\" headers=\"d216457e1996 \"><p class=\"p\">\n</p></td><td class=\"entry\" style=\"vertical-align:top;\" headers=\"d216457e2000 \"><p class=\"p\">\n</p></td><td class=\"entry\" style=\"vertical-align:top;\" headers=\"d216457e2004 \"><p class=\"p\">\n</p></td></tr><tr class=\"row\"><td class=\"entry\" style=\"vertical-align:top;\" headers=\"d216457e1992 \"><p class=\"p\"> 10/30/2001\n</p></td><td class=\"entry\" style=\"vertical-align:top;\" headers=\"d216457e1996 \"><p class=\"p\"> 100,000.00\n</p></td><td class=\"entry\" style=\"vertical-align:top;\" headers=\"d216457e2000 \"><p class=\"p\">\n</p></td><td class=\"entry\" style=\"vertical-align:top;\" headers=\"d216457e2004 \"><p class=\"p\"> 100,000.00\n</p></td></tr><tr class=\"row\"><td class=\"entry\" style=\"vertical-align:top;\" headers=\"d216457e1992 \"><p class=\"p\"> 01/30/2002\n</p></td><td class=\"entry\" style=\"vertical-align:top;\" headers=\"d216457e1996 \"><p class=\"p\">\n</p></td><td class=\"entry\" style=\"vertical-align:top;\" headers=\"d216457e2000 \"><p class=\"p\"> 6,000.00\n</p></td><td class=\"entry\" style=\"vertical-align:top;\" headers=\"d216457e2004 \"><p class=\"p\"> -6,000.00\n</p></td></tr><tr class=\"row\"><td class=\"entry\" style=\"vertical-align:top;\" headers=\"d216457e1992 \"><p class=\"p\"> 01/30/2003\n</p></td><td class=\"entry\" style=\"vertical-align:top;\" headers=\"d216457e1996 \"><p class=\"p\">\n</p></td><td class=\"entry\" style=\"vertical-align:top;\" headers=\"d216457e2000 \"><p class=\"p\"> 6,000.00\n</p></td><td class=\"entry\" style=\"vertical-align:top;\" headers=\"d216457e2004 \"><p class=\"p\"> -6,000.00\n</p></td></tr><tr class=\"row\"><td class=\"entry\" style=\"vertical-align:top;\" headers=\"d216457e1992 \"><p class=\"p\"> 04/30/2004\n</p></td><td class=\"entry\" style=\"vertical-align:top;\" headers=\"d216457e1996 \"><p class=\"p\">\n</p></td><td class=\"entry\" style=\"vertical-align:top;\" headers=\"d216457e2000 \"><p class=\"p\"> 106,000.00\n</p></td><td class=\"entry\" style=\"vertical-align:top;\" headers=\"d216457e2004 \"><p class=\"p\"> -106,000.00\n</p></td></tr></tbody></table></div>\n<p class=\"p\"><img class=\"inline\" src=\"loio4822705364e7771ee10000000a174cb4_LowRes.png\" alt=\"\" title=\"\"> The cash flow evaluation and the liquidity evaluation differ in that the cash flow evaluation displays cash flows for the interest commitment only.\n</p>\n</section></div>\n<div class=\"section\"><section class=\"section\" type=\"Liquidity evaluation\"><h2 class=\"section_title\">Liquidity evaluation</h2>\n<div class=\"table-wrapper tablenoborder\"><table summary=\"\" class=\"table\" frame=\"border\" border=\"1\" rules=\"all\"><colgroup><col width=\"20%\"><col width=\"20%\"><col width=\"20%\"><col width=\"20%\"><col width=\"20%\"></colgroup><thead class=\"thead\" style=\"text-align:left;\"><tr class=\"row\"><th class=\"entry\" style=\"vertical-align:top;\" id=\"d216457e2115\"><p class=\"p\"> Maturity band date\n</p></th><th class=\"entry\" style=\"vertical-align:top;\" id=\"d216457e2119\"><p class=\"p\"> Inpayment\n</p></th><th class=\"entry\" style=\"vertical-align:top;\" id=\"d216457e2123\"><p class=\"p\"> Disbursement\n</p></th><th class=\"entry\" style=\"vertical-align:top;\" id=\"d216457e2127\"><p class=\"p\"> Liquidity gap\n</p></th><th class=\"entry\" style=\"vertical-align:top;\" id=\"d216457e2131\"><p class=\"p\"> Cumulated liquidity gap\n</p></th></tr></thead><tbody class=\"tbody\"><tr class=\"row\"><td class=\"entry\" style=\"vertical-align:top;\" headers=\"d216457e2115 \"><p class=\"p\"> 10/29/2000\n</p></td><td class=\"entry\" style=\"vertical-align:top;\" headers=\"d216457e2119 \"><p class=\"p\">\n</p></td><td class=\"entry\" style=\"vertical-align:top;\" headers=\"d216457e2123 \"><p class=\"p\">\n</p></td><td class=\"entry\" style=\"vertical-align:top;\" headers=\"d216457e2127 \"><p class=\"p\">\n</p></td><td class=\"entry\" style=\"vertical-align:top;\" headers=\"d216457e2131 \"><p class=\"p\">\n</p></td></tr><tr class=\"row\"><td class=\"entry\" style=\"vertical-align:top;\" headers=\"d216457e2115 \"><p class=\"p\"> 10/30/2001\n</p></td><td class=\"entry\" style=\"vertical-align:top;\" headers=\"d216457e2119 \"><p class=\"p\"> 2,684.73\n</p></td><td class=\"entry\" style=\"vertical-align:top;\" headers=\"d216457e2123 \"><p class=\"p\">\n</p></td><td class=\"entry\" style=\"vertical-align:top;\" headers=\"d216457e2127 \"><p class=\"p\"> 2,684.73\n</p></td><td class=\"entry\" style=\"vertical-align:top;\" headers=\"d216457e2131 \"><p class=\"p\"> 2,684.73\n</p></td></tr><tr class=\"row\"><td class=\"entry\" style=\"vertical-align:top;\" headers=\"d216457e2115 \"><p class=\"p\"> 01/30/2002\n</p></td><td class=\"entry\" style=\"vertical-align:top;\" headers=\"d216457e2119 \"><p class=\"p\"> 833.95\n</p></td><td class=\"entry\" style=\"vertical-align:top;\" headers=\"d216457e2123 \"><p class=\"p\"> 6,000.00\n</p></td><td class=\"entry\" style=\"vertical-align:top;\" headers=\"d216457e2127 \"><p class=\"p\"> -5,166.05\n</p></td><td class=\"entry\" style=\"vertical-align:top;\" headers=\"d216457e2131 \"><p class=\"p\"> -2,481.32\n</p></td></tr><tr class=\"row\"><td class=\"entry\" style=\"vertical-align:top;\" headers=\"d216457e2115 \"><p class=\"p\"> 01/30/2003\n</p></td><td class=\"entry\" style=\"vertical-align:top;\" headers=\"d216457e2119 \"><p class=\"p\"> 2,586.13\n</p></td><td class=\"entry\" style=\"vertical-align:top;\" headers=\"d216457e2123 \"><p class=\"p\"> 6,000.00\n</p></td><td class=\"entry\" style=\"vertical-align:top;\" headers=\"d216457e2127 \"><p class=\"p\"> -3,413.87\n</p></td><td class=\"entry\" style=\"vertical-align:top;\" headers=\"d216457e2131 \"><p class=\"p\"> -5,895.19\n</p></td></tr><tr class=\"row\"><td class=\"entry\" style=\"vertical-align:top;\" headers=\"d216457e2115 \"><p class=\"p\"> 04/30/2004\n</p></td><td class=\"entry\" style=\"vertical-align:top;\" headers=\"d216457e2119 \"><p class=\"p\"> 3,503.71\n</p></td><td class=\"entry\" style=\"vertical-align:top;\" headers=\"d216457e2123 \"><p class=\"p\"> 6,000.00\n</p></td><td class=\"entry\" style=\"vertical-align:top;\" headers=\"d216457e2127 \"><p class=\"p\"> -2,496.29\n</p></td><td class=\"entry\" style=\"vertical-align:top;\" headers=\"d216457e2131 \"><p class=\"p\"> -8,391.48\n</p></td></tr></tbody></table></div>\n<p class=\"p\"><img class=\"inline\" src=\"loio4822705364e7771ee10000000a174cb4_LowRes.png\" alt=\"\" title=\"\"> The interest and capital payments flow into the liquidity evaluation in accordance with the capital commitment of the underlying transactions. Since the capital payments in a plain vanilla swap do not actually flow in reality, and only serve as a basis for the interest calculation, they are not taken into account in the liquidity evaluation. However, they are displayed in the other evaluations.\n</p>\n<p class=\"p\"><img class=\"inline\" src=\"loio4822705364e7771ee10000000a174cb4_LowRes.png\" alt=\"\" title=\"\"> How is the incoming payment of EUR 2,684.73 at the maturity band date 10/30/2001 calculated?\n</p>\n<p class=\"p\"> Up to 10/30/2001, variable interest flows on 03/05/2001, 06/05/2001 and 09/05/2001. The amount of the interest payment is determined using the forward rate calculated by the system for the relevant date. This results in the following figures:\n</p>\n<ul class=\"ul\"><li class=\"li\"><p class=\"p\"><span class=\"ph menucascade\"><img src=\"themes/sap-light/img/navstart.gif\" alt=\"Start of the navigation path\" title=\"Start of the navigation path\"><span class=\"ph uicontrol\">12/05/00 – 03/04/01 is 90 days, forward rate 2.8037511%</span>&nbsp;<img src=\"themes/sap-light/img/navstep.gif\" alt=\"Next navigation step\" title=\"Next navigation step\">&nbsp;<span class=\"ph uicontrol\">100,000.00 x 90/365 x 0.028037511 = 691.34.</span><img src=\"themes/sap-light/img/navend.gif\" alt=\"End of the navigation path\" title=\"End of the navigation path\"></span>\n</p></li><li class=\"li\"><p class=\"p\"><span class=\"ph menucascade\"><img src=\"themes/sap-light/img/navstart.gif\" alt=\"Start of the navigation path\" title=\"Start of the navigation path\"><span class=\"ph uicontrol\">03/05/01 – 06/04/01, 92 days, forward rate 3.8284709%</span>&nbsp;<img src=\"themes/sap-light/img/navstep.gif\" alt=\"Next navigation step\" title=\"Next navigation step\">&nbsp;<span class=\"ph uicontrol\"></span><img src=\"themes/sap-light/img/navend.gif\" alt=\"End of the navigation path\" title=\"End of the navigation path\"></span> 100,000.00 x 92/365 x 0.038284709 = 964.98.\n</p></li><li class=\"li\"><p class=\"p\"><span class=\"ph menucascade\"><img src=\"themes/sap-light/img/navstart.gif\" alt=\"Start of the navigation path\" title=\"Start of the navigation path\"><span class=\"ph uicontrol\">06/05/01 – 09/04/01, 92 days, forward rate 4.0801246%</span>&nbsp;<img src=\"themes/sap-light/img/navstep.gif\" alt=\"Next navigation step\" title=\"Next navigation step\">&nbsp;<span class=\"ph uicontrol\"></span><img src=\"themes/sap-light/img/navend.gif\" alt=\"End of the navigation path\" title=\"End of the navigation path\"></span> 100,000.00 x 92/365 x 0.040801246 = 1028.41.\n</p></li></ul>\n<p class=\"p\"> This gives a total amount of EUR 2,684.73.\n</p>\n</section></div>\n<div class=\"section\"><section class=\"section\" type=\"Currency liquidity\"><h2 class=\"section_title\">Currency liquidity</h2>\n<div class=\"table-wrapper tablenoborder\"><table summary=\"\" class=\"table\" frame=\"border\" border=\"1\" rules=\"all\"><colgroup><col width=\"14.285714285714286%\"><col width=\"14.285714285714286%\"><col width=\"14.285714285714286%\"><col width=\"14.285714285714286%\"><col width=\"14.285714285714286%\"><col width=\"14.285714285714286%\"><col width=\"14.285714285714286%\"></colgroup><thead class=\"thead\" style=\"text-align:left;\"><tr class=\"row\"><th class=\"entry\" style=\"vertical-align:top;\" id=\"d216457e2303\"><p class=\"p\"> Maturity band date\n</p></th><th class=\"entry\" style=\"vertical-align:top;\" id=\"d216457e2307\"><p class=\"p\"> Transaction currency\n</p></th><th class=\"entry\" style=\"vertical-align:top;\" id=\"d216457e2311\"><p class=\"p\"> Inpayment\n</p></th><th class=\"entry\" style=\"vertical-align:top;\" id=\"d216457e2315\"><p class=\"p\"> Disbursement\n</p></th><th class=\"entry\" style=\"vertical-align:top;\" id=\"d216457e2319\"><p class=\"p\"> Liquidity gap\n</p></th><th class=\"entry\" style=\"vertical-align:top;\" id=\"d216457e2323\"><p class=\"p\"> Cumulated liquidity gap\n</p></th><th class=\"entry\" style=\"vertical-align:top;\" id=\"d216457e2327\"><p class=\"p\"> Evaluation currency or transaction currency (as per the setting for the data relevant for display)\n</p></th></tr></thead><tbody class=\"tbody\"><tr class=\"row\"><td class=\"entry\" style=\"vertical-align:top;\" headers=\"d216457e2303 \"><p class=\"p\"> 10/29/2000\n</p></td><td class=\"entry\" style=\"vertical-align:top;\" headers=\"d216457e2307 \"><p class=\"p\"> EUR\n</p></td><td class=\"entry\" style=\"vertical-align:top;\" headers=\"d216457e2311 \"><p class=\"p\">\n</p></td><td class=\"entry\" style=\"vertical-align:top;\" headers=\"d216457e2315 \"><p class=\"p\">\n</p></td><td class=\"entry\" style=\"vertical-align:top;\" headers=\"d216457e2319 \"><p class=\"p\">\n</p></td><td class=\"entry\" style=\"vertical-align:top;\" headers=\"d216457e2323 \"><p class=\"p\">\n</p></td><td class=\"entry\" style=\"vertical-align:top;\" headers=\"d216457e2327 \"><p class=\"p\"> EUR\n</p></td></tr><tr class=\"row\"><td class=\"entry\" style=\"vertical-align:top;\" headers=\"d216457e2303 \"><p class=\"p\"> 10/30/2001\n</p></td><td class=\"entry\" style=\"vertical-align:top;\" headers=\"d216457e2307 \"><p class=\"p\"> EUR\n</p></td><td class=\"entry\" style=\"vertical-align:top;\" headers=\"d216457e2311 \"><p class=\"p\"> 2,684.73\n</p></td><td class=\"entry\" style=\"vertical-align:top;\" headers=\"d216457e2315 \"><p class=\"p\">\n</p></td><td class=\"entry\" style=\"vertical-align:top;\" headers=\"d216457e2319 \"><p class=\"p\"> 2,684.73\n</p></td><td class=\"entry\" style=\"vertical-align:top;\" headers=\"d216457e2323 \"><p class=\"p\"> 2,684.73\n</p></td><td class=\"entry\" style=\"vertical-align:top;\" headers=\"d216457e2327 \"><p class=\"p\"> EUR\n</p></td></tr><tr class=\"row\"><td class=\"entry\" style=\"vertical-align:top;\" headers=\"d216457e2303 \"><p class=\"p\"> 01/30/2002\n</p></td><td class=\"entry\" style=\"vertical-align:top;\" headers=\"d216457e2307 \"><p class=\"p\"> EUR\n</p></td><td class=\"entry\" style=\"vertical-align:top;\" headers=\"d216457e2311 \"><p class=\"p\"> 833.95\n</p></td><td class=\"entry\" style=\"vertical-align:top;\" headers=\"d216457e2315 \"><p class=\"p\"> 6,000.00\n</p></td><td class=\"entry\" style=\"vertical-align:top;\" headers=\"d216457e2319 \"><p class=\"p\"> -5,166.05\n</p></td><td class=\"entry\" style=\"vertical-align:top;\" headers=\"d216457e2323 \"><p class=\"p\"> -2,481.32\n</p></td><td class=\"entry\" style=\"vertical-align:top;\" headers=\"d216457e2327 \"><p class=\"p\"> EUR\n</p></td></tr><tr class=\"row\"><td class=\"entry\" style=\"vertical-align:top;\" headers=\"d216457e2303 \"><p class=\"p\"> 01/30/2003\n</p></td><td class=\"entry\" style=\"vertical-align:top;\" headers=\"d216457e2307 \"><p class=\"p\"> EUR\n</p></td><td class=\"entry\" style=\"vertical-align:top;\" headers=\"d216457e2311 \"><p class=\"p\"> 2,586.13\n</p></td><td class=\"entry\" style=\"vertical-align:top;\" headers=\"d216457e2315 \"><p class=\"p\"> 6,000.00\n</p></td><td class=\"entry\" style=\"vertical-align:top;\" headers=\"d216457e2319 \"><p class=\"p\"> -3,413.87\n</p></td><td class=\"entry\" style=\"vertical-align:top;\" headers=\"d216457e2323 \"><p class=\"p\"> -5,895.19\n</p></td><td class=\"entry\" style=\"vertical-align:top;\" headers=\"d216457e2327 \"><p class=\"p\"> EUR\n</p></td></tr><tr class=\"row\"><td class=\"entry\" style=\"vertical-align:top;\" headers=\"d216457e2303 \"><p class=\"p\"> 04/30/2004\n</p></td><td class=\"entry\" style=\"vertical-align:top;\" headers=\"d216457e2307 \"><p class=\"p\"> EUR\n</p></td><td class=\"entry\" style=\"vertical-align:top;\" headers=\"d216457e2311 \"><p class=\"p\"> 3,503.71\n</p></td><td class=\"entry\" style=\"vertical-align:top;\" headers=\"d216457e2315 \"><p class=\"p\"> 6,000.00\n</p></td><td class=\"entry\" style=\"vertical-align:top;\" headers=\"d216457e2319 \"><p class=\"p\"> -2,496.29\n</p></td><td class=\"entry\" style=\"vertical-align:top;\" headers=\"d216457e2323 \"><p class=\"p\"> -8,391.48\n</p></td><td class=\"entry\" style=\"vertical-align:top;\" headers=\"d216457e2327 \"><p class=\"p\"> EUR\n</p></td></tr></tbody></table></div>\n</section></div>\n<div class=\"section\"><section class=\"section\" type=\"Net interest income evaluation\"><h2 class=\"section_title\">Net interest income evaluation</h2>\n<div class=\"table-wrapper tablenoborder\"><table summary=\"\" class=\"table\" frame=\"border\" border=\"1\" rules=\"all\"><colgroup><col width=\"16.666666666666668%\"><col width=\"16.666666666666668%\"><col width=\"16.666666666666668%\"><col width=\"16.666666666666668%\"><col width=\"16.666666666666668%\"><col width=\"16.666666666666668%\"></colgroup><thead class=\"thead\" style=\"text-align:left;\"><tr class=\"row\"><th class=\"entry\" style=\"vertical-align:top;\" id=\"d216457e2494\"><p class=\"p\"> Maturity band date\n</p></th><th class=\"entry\" style=\"vertical-align:top;\" id=\"d216457e2498\"><p class=\"p\"> Interest revenue from product interest rate\n</p></th><th class=\"entry\" style=\"vertical-align:top;\" id=\"d216457e2502\"><p class=\"p\"> Interest revenue (opportunity interest rate)\n</p></th><th class=\"entry\" style=\"vertical-align:top;\" id=\"d216457e2506\"><p class=\"p\"> Interest expense (product interest rate)\n</p></th><th class=\"entry\" style=\"vertical-align:top;\" id=\"d216457e2510\"><p class=\"p\"> Interest expense (opportunity interest rate)\n</p></th><th class=\"entry\" style=\"vertical-align:top;\" id=\"d216457e2514\"><p class=\"p\"> Absolute interest income\n</p></th></tr></thead><tbody class=\"tbody\"><tr class=\"row\"><td class=\"entry\" style=\"vertical-align:top;\" headers=\"d216457e2494 \"><p class=\"p\"> 10/29/2000\n</p></td><td class=\"entry\" style=\"vertical-align:top;\" headers=\"d216457e2498 \"><p class=\"p\">\n</p></td><td class=\"entry\" style=\"vertical-align:top;\" headers=\"d216457e2502 \"><p class=\"p\">\n</p></td><td class=\"entry\" style=\"vertical-align:top;\" headers=\"d216457e2506 \"><p class=\"p\">\n</p></td><td class=\"entry\" style=\"vertical-align:top;\" headers=\"d216457e2510 \"><p class=\"p\">\n</p></td><td class=\"entry\" style=\"vertical-align:top;\" headers=\"d216457e2514 \"><p class=\"p\">\n</p></td></tr><tr class=\"row\"><td class=\"entry\" style=\"vertical-align:top;\" headers=\"d216457e2494 \"><p class=\"p\"> 10/30/2001\n</p></td><td class=\"entry\" style=\"vertical-align:top;\" headers=\"d216457e2498 \"><p class=\"p\"> 3.197,93\n</p></td><td class=\"entry\" style=\"vertical-align:top;\" headers=\"d216457e2502 \"><p class=\"p\"> 3.197,93\n</p></td><td class=\"entry\" style=\"vertical-align:top;\" headers=\"d216457e2506 \"><p class=\"p\"> 5.424,66\n</p></td><td class=\"entry\" style=\"vertical-align:top;\" headers=\"d216457e2510 \"><p class=\"p\"> 5.424,66\n</p></td><td class=\"entry\" style=\"vertical-align:top;\" headers=\"d216457e2514 \"><p class=\"p\"> -2.226,73\n</p></td></tr><tr class=\"row\"><td class=\"entry\" style=\"vertical-align:top;\" headers=\"d216457e2494 \"><p class=\"p\"> 01/30/2002\n</p></td><td class=\"entry\" style=\"vertical-align:top;\" headers=\"d216457e2498 \"><p class=\"p\"> 765,45\n</p></td><td class=\"entry\" style=\"vertical-align:top;\" headers=\"d216457e2502 \"><p class=\"p\"> 765,45\n</p></td><td class=\"entry\" style=\"vertical-align:top;\" headers=\"d216457e2506 \"><p class=\"p\"> 1.512,33\n</p></td><td class=\"entry\" style=\"vertical-align:top;\" headers=\"d216457e2510 \"><p class=\"p\"> 1.512,33\n</p></td><td class=\"entry\" style=\"vertical-align:top;\" headers=\"d216457e2514 \"><p class=\"p\"> -746,88\n</p></td></tr><tr class=\"row\"><td class=\"entry\" style=\"vertical-align:top;\" headers=\"d216457e2494 \"><p class=\"p\"> 01/30/2003\n</p></td><td class=\"entry\" style=\"vertical-align:top;\" headers=\"d216457e2498 \"><p class=\"p\"> 2.658,23\n</p></td><td class=\"entry\" style=\"vertical-align:top;\" headers=\"d216457e2502 \"><p class=\"p\"> 2.658,23\n</p></td><td class=\"entry\" style=\"vertical-align:top;\" headers=\"d216457e2506 \"><p class=\"p\"> 6,000.00\n</p></td><td class=\"entry\" style=\"vertical-align:top;\" headers=\"d216457e2510 \"><p class=\"p\"> 6,000.00\n</p></td><td class=\"entry\" style=\"vertical-align:top;\" headers=\"d216457e2514 \"><p class=\"p\"> -3.341,77\n</p></td></tr><tr class=\"row\"><td class=\"entry\" style=\"vertical-align:top;\" headers=\"d216457e2494 \"><p class=\"p\"> 04/30/2004\n</p></td><td class=\"entry\" style=\"vertical-align:top;\" headers=\"d216457e2498 \"><p class=\"p\"> 2.986,92\n</p></td><td class=\"entry\" style=\"vertical-align:top;\" headers=\"d216457e2502 \"><p class=\"p\"> 2.986,92\n</p></td><td class=\"entry\" style=\"vertical-align:top;\" headers=\"d216457e2506 \"><p class=\"p\"> 5.063,01\n</p></td><td class=\"entry\" style=\"vertical-align:top;\" headers=\"d216457e2510 \"><p class=\"p\"> 5.063,01\n</p></td><td class=\"entry\" style=\"vertical-align:top;\" headers=\"d216457e2514 \"><p class=\"p\"> -2.076,09\n</p></td></tr></tbody></table></div>\n<p class=\"p\"><img class=\"inline\" src=\"loio4822705364e7771ee10000000a174cb4_LowRes.png\" alt=\"\" title=\"\"> How is the interest revenue for product interest of EUR 3,197.93 at the maturity band date 10/30/2001 calculated?\n</p>\n<p class=\"p\"> The net interest income evaluation displays the net interest income of a bank distributed over time. The basis for the net interest income calculation are the values determined in the average position evaluation. Note, however, that the average positions determined in the average position evaluation are calculated taking account of the maturity band. This means they are calculated on the basis of 365 or 366 days. In the net interest income evaluation, the interest calculation method defined in the ALM evaluation type is taken into account instead. Using the act/360 interest calculation method makes no difference in this case.\n</p>\n<p class=\"p\"> The amount EUR 3,197.93 is calculated as follows:\n</p>\n<ul class=\"ul\"><li class=\"li\"><p class=\"p\"><span class=\"ph menucascade\"><img src=\"themes/sap-light/img/navstart.gif\" alt=\"Start of the navigation path\" title=\"Start of the navigation path\"><span class=\"ph uicontrol\">10/30/00 – 10/30/01,. 366 days, forward rate 3.5371046%</span>&nbsp;<img src=\"themes/sap-light/img/navstep.gif\" alt=\"Next navigation step\" title=\"Next navigation step\">&nbsp;<span class=\"ph uicontrol\">90,163.93 x 366/365 x 0.035371046 = 3,197.93</span><img src=\"themes/sap-light/img/navend.gif\" alt=\"End of the navigation path\" title=\"End of the navigation path\"></span>\n</p></li></ul>\n<p class=\"p\"><img class=\"inline\" src=\"loio4822705364e7771ee10000000a174cb4_LowRes.png\" alt=\"\" title=\"\"> How is the interest revenue for product interest amounting to EUR 5,424.66 at the maturity band date 03/30/2001 calculated?\n</p>\n<p class=\"p\"> The amount EUR 5,424.66 is calculated as follows:\n</p>\n<ul class=\"ul\"><li class=\"li\"><p class=\"p\"><span class=\"ph menucascade\"><img src=\"themes/sap-light/img/navstart.gif\" alt=\"Start of the navigation path\" title=\"Start of the navigation path\"><span class=\"ph uicontrol\">10/30/00 -10/30/01, 366 days</span>&nbsp;<img src=\"themes/sap-light/img/navstep.gif\" alt=\"Next navigation step\" title=\"Next navigation step\">&nbsp;<span class=\"ph uicontrol\">90,163.93 x 0.06 x 366/365 = EUR 5,424.66.</span><img src=\"themes/sap-light/img/navend.gif\" alt=\"End of the navigation path\" title=\"End of the navigation path\"></span>\n</p></li></ul>\n</section></div>\n</div></div></section><div class=\"clear\"></div>\n</div></div></div></body></html>"
}