{
  "loio": "3c04c55368511d4be10000000a174cb4",
  "title": "Sample Bank Selection and Control of Available Amounts",
  "file_path": "3c04c55368511d4be10000000a174cb4.html",
  "page_id": 2555102167,
  "github_link": "",
  "toc_path": [
    "Treasury and Risk Management",
    "Transaction Manager",
    "Accounting",
    "Payment",
    "Payment Program for Payment Requests (FI-BL)",
    "Execution of the Payment Program",
    "Selecting Banks and Planning Available Amounts",
    "Sample Bank Selection and Control of Available Amounts"
  ],
  "depth": 7,
  "body_html": "<!DOCTYPE html\n  SYSTEM \"about:legacy-compat\">\n<html lang=\"en-us\" dir=\"ltr\"><head><title>Sample Bank Selection and Control of Available Amounts</title><meta charset=\"utf-8\"><link rel=\"stylesheet\" type=\"text/css\" media=\"screen,projection\" href=\"/resource/css/style-v2.css\"><script type=\"text/javascript\" src=\"js/sap-strings.js\"></script></head><body class=\"en-us sap-light centered navigation-default enumeration-disabled\"><div id=\"d4h5-main-container\" class=\"container_12\" role=\"application\"><div id=\"d4h5-section-container\" class=\"grid_12\"><div id=\"d4h5-main-content\" class=\"grid_8 alpha omega\"><section><div class=\"page topic  - topic-topic \" id=\"loio3c04c55368511d4be10000000a174cb4\"><h1 class=\"title topictitle1\">Sample Bank Selection and Control of Available Amounts</h1><div class=\"body\">\n<p class=\"p\">You want to use the payment program to pay five open items to five different suppliers:</p>\n<ul class=\"ul\" id=\"loio3c04c55368511d4be10000000a174cb4__ul_jbn_1pw_kbc\">\n<li class=\"li\"><p class=\"p\">Payment to first supplier 40,000</p></li>\n<li class=\"li\"><p class=\"p\">Payment to second supplier 30,000</p></li>\n<li class=\"li\"><p class=\"p\">Payment to third supplier 20,000</p></li>\n<li class=\"li\"><p class=\"p\">Payment to fourth supplier 7,000</p></li>\n<li class=\"li\"><p class=\"p\">Payment to fifth supplier 12,000</p></li>\n</ul>\n<p class=\"p\"><span class=\"ph emphasis emphasis\">Sample Bank Selection</span></p>\n<div class=\"table-wrapper tablenoborder\"><table summary=\"\" id=\"loio3c04c55368511d4be10000000a174cb4__table_bph_hpw_kbc\" class=\"table\" data-table-id=\"table_bph_hpw_kbc\" frame=\"border\" border=\"1\" rules=\"all\"><colgroup><col width=\"25%\"><col width=\"25%\"><col width=\"25%\"><col width=\"25%\"></colgroup><thead class=\"thead\" style=\"text-align:left;\">\n<tr class=\"row\">\n<th class=\"entry\" style=\"vertical-align:top;\" id=\"d570353e116\"><p>Available Amounts for Automatic Payments</p></th>\n<th class=\"entry\" style=\"vertical-align:top;\" id=\"d570353e119\"><p>Bank A Prio 2</p></th>\n<th class=\"entry\" style=\"vertical-align:top;\" id=\"d570353e122\"><p>Bank B Prio 1</p></th>\n<th class=\"entry\" style=\"vertical-align:top;\" id=\"d570353e125\"><p>Note</p></th>\n</tr>\n</thead><tbody class=\"tbody\">\n<tr class=\"row\">\n<td class=\"entry\" style=\"vertical-align:top;\" headers=\"d570353e116 \"><p>Before debit memo from first customer</p></td>\n<td class=\"entry\" style=\"vertical-align:top;\" headers=\"d570353e119 \"><p>70,000</p></td>\n<td class=\"entry\" style=\"vertical-align:top;\" headers=\"d570353e122 \"><p>50,000</p></td>\n<td class=\"entry\" style=\"vertical-align:top;\" headers=\"d570353e125 \">&nbsp;</td>\n</tr>\n<tr class=\"row\">\n<td class=\"entry\" style=\"vertical-align:top;\" headers=\"d570353e116 \"><p>After debit memo for first customer (40,000)</p></td>\n<td class=\"entry\" style=\"vertical-align:top;\" headers=\"d570353e119 \"><p>70,000</p></td>\n<td class=\"entry\" style=\"vertical-align:top;\" headers=\"d570353e122 \"><p>10,000</p></td>\n<td class=\"entry\" style=\"vertical-align:top;\" headers=\"d570353e125 \"><p>Bank B Prio 1</p></td>\n</tr>\n<tr class=\"row\">\n<td class=\"entry\" style=\"vertical-align:top;\" headers=\"d570353e116 \"><p>After debit memo for second customer (30,000)</p></td>\n<td class=\"entry\" style=\"vertical-align:top;\" headers=\"d570353e119 \"><p>40,000</p></td>\n<td class=\"entry\" style=\"vertical-align:top;\" headers=\"d570353e122 \"><p>10,000</p></td>\n<td class=\"entry\" style=\"vertical-align:top;\" headers=\"d570353e125 \"><p>Insufficient amount at bank B</p></td>\n</tr>\n<tr class=\"row\">\n<td class=\"entry\" style=\"vertical-align:top;\" headers=\"d570353e116 \"><p>After debit memo for third customer (20,000)</p></td>\n<td class=\"entry\" style=\"vertical-align:top;\" headers=\"d570353e119 \"><p>20,000</p></td>\n<td class=\"entry\" style=\"vertical-align:top;\" headers=\"d570353e122 \"><p>10,000</p></td>\n<td class=\"entry\" style=\"vertical-align:top;\" headers=\"d570353e125 \"><p>Insufficient amount at bank B</p></td>\n</tr>\n<tr class=\"row\">\n<td class=\"entry\" style=\"vertical-align:top;\" headers=\"d570353e116 \"><p>After debit memo for fourth customer (7,000)</p></td>\n<td class=\"entry\" style=\"vertical-align:top;\" headers=\"d570353e119 \"><p>20,000</p></td>\n<td class=\"entry\" style=\"vertical-align:top;\" headers=\"d570353e122 \"><p>3,000</p></td>\n<td class=\"entry\" style=\"vertical-align:top;\" headers=\"d570353e125 \"><p>Bank B Prio 1</p></td>\n</tr>\n<tr class=\"row\">\n<td class=\"entry\" style=\"vertical-align:top;\" headers=\"d570353e116 \"><p>After debit memo for fifth customer (12,000)</p></td>\n<td class=\"entry\" style=\"vertical-align:top;\" headers=\"d570353e119 \"><p>8,000</p></td>\n<td class=\"entry\" style=\"vertical-align:top;\" headers=\"d570353e122 \"><p>3,000</p></td>\n<td class=\"entry\" style=\"vertical-align:top;\" headers=\"d570353e125 \"><p>Insufficient amount at bank B</p></td>\n</tr>\n</tbody></table></div>\n</div></div></section><div class=\"clear\"></div>\n</div></div></div></body></html>"
}